{
"meta":{"test_sets":[],"test_metrics":[],"learn_metrics":[{"best_value":"Min","name":"RMSE"}],"launch_mode":"Train","parameters":"","iteration_count":1000,"learn_sets":["learn"],"name":"experiment"},
"iterations":[
{"learn":[79.19366124],"iteration":0,"passed_time":0.01224507474,"remaining_time":12.23282967},
{"learn":[78.44993448],"iteration":1,"passed_time":0.01917075244,"remaining_time":9.566205465},
{"learn":[77.63885858],"iteration":2,"passed_time":0.02694044652,"remaining_time":8.953208392},
{"learn":[76.88644403],"iteration":3,"passed_time":0.03328209916,"remaining_time":8.287242691},
{"learn":[76.14028547],"iteration":4,"passed_time":0.03926685558,"remaining_time":7.814104261},
{"learn":[75.4508083],"iteration":5,"passed_time":0.04755015477,"remaining_time":7.87747564},
{"learn":[74.7519955],"iteration":6,"passed_time":0.05610163495,"remaining_time":7.958417644},
{"learn":[74.09487469],"iteration":7,"passed_time":0.0620041558,"remaining_time":7.688515319},
{"learn":[73.49330695],"iteration":8,"passed_time":0.06771826075,"remaining_time":7.456532933},
{"learn":[72.8847015],"iteration":9,"passed_time":0.07343332436,"remaining_time":7.269899111},
{"learn":[72.2913517],"iteration":10,"passed_time":0.07921283858,"remaining_time":7.121954305},
{"learn":[71.78802448],"iteration":11,"passed_time":0.08482772765,"remaining_time":6.984149576},
{"learn":[71.23638583],"iteration":12,"passed_time":0.09059866674,"remaining_time":6.878529544},
{"learn":[70.74168695],"iteration":13,"passed_time":0.09580170768,"remaining_time":6.747177412},
{"learn":[70.30193071],"iteration":14,"passed_time":0.101460473,"remaining_time":6.662571059},
{"learn":[69.83754995],"iteration":15,"passed_time":0.1069308925,"remaining_time":6.576249891},
{"learn":[69.36463589],"iteration":16,"passed_time":0.1119796308,"remaining_time":6.475057476},
{"learn":[68.88473047],"iteration":17,"passed_time":0.117123024,"remaining_time":6.389711645},
{"learn":[68.461609],"iteration":18,"passed_time":0.1235775877,"remaining_time":6.380505976},
{"learn":[68.06157764],"iteration":19,"passed_time":0.1294178067,"remaining_time":6.34147253},
{"learn":[67.67056912],"iteration":20,"passed_time":0.1350297073,"remaining_time":6.294956353},
{"learn":[67.28241338],"iteration":21,"passed_time":0.1407541643,"remaining_time":6.257162396},
{"learn":[66.85386576],"iteration":22,"passed_time":0.1462335709,"remaining_time":6.211747774},
{"learn":[66.48970019],"iteration":23,"passed_time":0.1518135671,"remaining_time":6.17375173},
{"learn":[66.11898062],"iteration":24,"passed_time":0.1572959782,"remaining_time":6.13454315},
{"learn":[65.7524684],"iteration":25,"passed_time":0.1630359197,"remaining_time":6.107576377},
{"learn":[65.43299335],"iteration":26,"passed_time":0.1684042497,"remaining_time":6.068790183},
{"learn":[65.09657165],"iteration":27,"passed_time":0.1741870992,"remaining_time":6.046780729},
{"learn":[64.80691419],"iteration":28,"passed_time":0.1798071342,"remaining_time":6.020438874},
{"learn":[64.49298708],"iteration":29,"passed_time":0.1849512692,"remaining_time":5.980091039},
{"learn":[64.19029347],"iteration":30,"passed_time":0.1904444006,"remaining_time":5.95292336},
{"learn":[63.91707324],"iteration":31,"passed_time":0.1959408854,"remaining_time":5.927211785},
{"learn":[63.64266799],"iteration":32,"passed_time":0.2024481825,"remaining_time":5.932345227},
{"learn":[63.35879908],"iteration":33,"passed_time":0.2082203988,"remaining_time":5.915908977},
{"learn":[63.1078925],"iteration":34,"passed_time":0.2139354428,"remaining_time":5.89850578},
{"learn":[62.85755416],"iteration":35,"passed_time":0.2195279504,"remaining_time":5.878470672},
{"learn":[62.59090137],"iteration":36,"passed_time":0.2262307235,"remaining_time":5.888113155},
{"learn":[62.3275739],"iteration":37,"passed_time":0.2328774106,"remaining_time":5.8954755},
{"learn":[62.03926163],"iteration":38,"passed_time":0.2398492268,"remaining_time":5.910130947},
{"learn":[61.81795034],"iteration":39,"passed_time":0.2453883034,"remaining_time":5.889319282},
{"learn":[61.58475636],"iteration":40,"passed_time":0.2508195334,"remaining_time":5.866730063},
{"learn":[61.3872657],"iteration":41,"passed_time":0.2566798749,"remaining_time":5.854745717},
{"learn":[61.17876688],"iteration":42,"passed_time":0.2619641677,"remaining_time":5.830225778},
{"learn":[60.95849101],"iteration":43,"passed_time":0.2677032516,"remaining_time":5.816461558},
{"learn":[60.76502344],"iteration":44,"passed_time":0.2738740405,"remaining_time":5.812215749},
{"learn":[60.58512618],"iteration":45,"passed_time":0.2803742888,"remaining_time":5.814718947},
{"learn":[60.4059616],"iteration":46,"passed_time":0.2864729674,"remaining_time":5.808696551},
{"learn":[60.19872742],"iteration":47,"passed_time":0.2920215997,"remaining_time":5.791761727},
{"learn":[59.99865759],"iteration":48,"passed_time":0.2980553391,"remaining_time":5.784706684},
{"learn":[59.82661615],"iteration":49,"passed_time":0.3036540525,"remaining_time":5.769426998},
{"learn":[59.65508428],"iteration":50,"passed_time":0.3091900244,"remaining_time":5.753359474},
{"learn":[59.47357686],"iteration":51,"passed_time":0.3147593254,"remaining_time":5.738304625},
{"learn":[59.29484587],"iteration":52,"passed_time":0.3214317653,"remaining_time":5.743318523},
{"learn":[59.13795905],"iteration":53,"passed_time":0.3270899469,"remaining_time":5.730131292},
{"learn":[58.98159584],"iteration":54,"passed_time":0.3330439035,"remaining_time":5.722299796},
{"learn":[58.80583396],"iteration":55,"passed_time":0.3385633184,"remaining_time":5.707210224},
{"learn":[58.66341644],"iteration":56,"passed_time":0.344067653,"remaining_time":5.692206961},
{"learn":[58.52910994],"iteration":57,"passed_time":0.3499233765,"remaining_time":5.683238287},
{"learn":[58.39088146],"iteration":58,"passed_time":0.3582445639,"remaining_time":5.713697197},
{"learn":[58.2445597],"iteration":59,"passed_time":0.3635607551,"remaining_time":5.695785163},
{"learn":[58.09007769],"iteration":60,"passed_time":0.3694044998,"remaining_time":5.686406973},
{"learn":[57.93451791],"iteration":61,"passed_time":0.3748884109,"remaining_time":5.671698861},
{"learn":[57.79088814],"iteration":62,"passed_time":0.3804239932,"remaining_time":5.65805209},
{"learn":[57.66384675],"iteration":63,"passed_time":0.3864377834,"remaining_time":5.651652582},
{"learn":[57.50783618],"iteration":64,"passed_time":0.3920448441,"remaining_time":5.639414297},
{"learn":[57.37936308],"iteration":65,"passed_time":0.397200176,"remaining_time":5.620984309},
{"learn":[57.20162798],"iteration":66,"passed_time":0.40312254,"remaining_time":5.613631788},
{"learn":[57.07107476],"iteration":67,"passed_time":0.4085364972,"remaining_time":5.599353167},
{"learn":[56.95237333],"iteration":68,"passed_time":0.4142340424,"remaining_time":5.589157876},
{"learn":[56.85112267],"iteration":69,"passed_time":0.4198734799,"remaining_time":5.57831909},
{"learn":[56.7411168],"iteration":70,"passed_time":0.4251382814,"remaining_time":5.562724836},
{"learn":[56.63177295],"iteration":71,"passed_time":0.4308022295,"remaining_time":5.55256207},
{"learn":[56.48722134],"iteration":72,"passed_time":0.4371199456,"remaining_time":5.550824515},
{"learn":[56.38782879],"iteration":73,"passed_time":0.4426038125,"remaining_time":5.538528789},
{"learn":[56.27715593],"iteration":74,"passed_time":0.4479728268,"remaining_time":5.524998197},
{"learn":[56.15488412],"iteration":75,"passed_time":0.4535953178,"remaining_time":5.514764127},
{"learn":[56.04831304],"iteration":76,"passed_time":0.4589484804,"remaining_time":5.501421395},
{"learn":[55.95997447],"iteration":77,"passed_time":0.4645127803,"remaining_time":5.490779275},
{"learn":[55.85190992],"iteration":78,"passed_time":0.4704338958,"remaining_time":5.484425545},
{"learn":[55.75052599],"iteration":79,"passed_time":0.4758998989,"remaining_time":5.472848837},
{"learn":[55.65415388],"iteration":80,"passed_time":0.4812106369,"remaining_time":5.459661424},
{"learn":[55.55804487],"iteration":81,"passed_time":0.4867922243,"remaining_time":5.449698315},
{"learn":[55.45100287],"iteration":82,"passed_time":0.492728708,"remaining_time":5.44376175},
{"learn":[55.31384205],"iteration":83,"passed_time":0.4986400222,"remaining_time":5.437550718},
{"learn":[55.2389654],"iteration":84,"passed_time":0.5040475818,"remaining_time":5.425923969},
{"learn":[55.14796705],"iteration":85,"passed_time":0.5095643585,"remaining_time":5.415602601},
{"learn":[55.06796608],"iteration":86,"passed_time":0.5160584193,"remaining_time":5.41564755},
{"learn":[54.97360364],"iteration":87,"passed_time":0.5213052403,"remaining_time":5.402617945},
{"learn":[54.88767678],"iteration":88,"passed_time":0.5270878009,"remaining_time":5.395247041},
{"learn":[54.81680847],"iteration":89,"passed_time":0.5326586525,"remaining_time":5.38577082},
{"learn":[54.70935292],"iteration":90,"passed_time":0.5385578968,"remaining_time":5.37966075},
{"learn":[54.62010545],"iteration":91,"passed_time":0.5446486418,"remaining_time":5.37544529},
{"learn":[54.52839157],"iteration":92,"passed_time":0.5509232667,"remaining_time":5.372982827},
{"learn":[54.4097289],"iteration":93,"passed_time":0.5567031769,"remaining_time":5.365671045},
{"learn":[54.3189903],"iteration":94,"passed_time":0.5628171002,"remaining_time":5.361573428},
{"learn":[54.20546433],"iteration":95,"passed_time":0.5690301126,"remaining_time":5.358366894},
{"learn":[54.12890826],"iteration":96,"passed_time":0.5747253036,"remaining_time":5.350277826},
{"learn":[54.03634019],"iteration":97,"passed_time":0.5818950097,"remaining_time":5.355809171},
{"learn":[53.96421047],"iteration":98,"passed_time":0.588941271,"remaining_time":5.359960456},
{"learn":[53.89637395],"iteration":99,"passed_time":0.5950248099,"remaining_time":5.355223289},
{"learn":[53.81741451],"iteration":100,"passed_time":0.6012672936,"remaining_time":5.351874228},
{"learn":[53.74680084],"iteration":101,"passed_time":0.6073709104,"remaining_time":5.347245858},
{"learn":[53.66481448],"iteration":102,"passed_time":0.6138978669,"remaining_time":5.346275598},
{"learn":[53.58206077],"iteration":103,"passed_time":0.6198139339,"remaining_time":5.33993543},
{"learn":[53.49574094],"iteration":104,"passed_time":0.6259002136,"remaining_time":5.335054201},
{"learn":[53.44989075],"iteration":105,"passed_time":0.6326153408,"remaining_time":5.335453912},
{"learn":[53.38794883],"iteration":106,"passed_time":0.6387164042,"remaining_time":5.330595784},
{"learn":[53.30965202],"iteration":107,"passed_time":0.6455206682,"remaining_time":5.331522556},
{"learn":[53.25185513],"iteration":108,"passed_time":0.6515165445,"remaining_time":5.32569946},
{"learn":[53.186637],"iteration":109,"passed_time":0.6577768441,"remaining_time":5.322012648},
{"learn":[53.12287278],"iteration":110,"passed_time":0.6654448427,"remaining_time":5.32955374},
{"learn":[53.06606632],"iteration":111,"passed_time":0.6712868629,"remaining_time":5.322345841},
{"learn":[52.99032642],"iteration":112,"passed_time":0.6782623702,"remaining_time":5.32405949},
{"learn":[52.91886287],"iteration":113,"passed_time":0.6873015993,"remaining_time":5.341659798},
{"learn":[52.84857433],"iteration":114,"passed_time":0.6940028278,"remaining_time":5.34080437},
{"learn":[52.78251062],"iteration":115,"passed_time":0.7016382241,"remaining_time":5.346967156},
{"learn":[52.71766059],"iteration":116,"passed_time":0.7071729498,"remaining_time":5.337040296},
{"learn":[52.65097243],"iteration":117,"passed_time":0.7142199523,"remaining_time":5.338491508},
{"learn":[52.59238454],"iteration":118,"passed_time":0.7201724819,"remaining_time":5.331697114},
{"learn":[52.530209],"iteration":119,"passed_time":0.7267254873,"remaining_time":5.32932024},
{"learn":[52.47021081],"iteration":120,"passed_time":0.7322712017,"remaining_time":5.319556911},
{"learn":[52.41009196],"iteration":121,"passed_time":0.739630251,"remaining_time":5.32291279},
{"learn":[52.36047127],"iteration":122,"passed_time":0.746247358,"remaining_time":5.320804333},
{"learn":[52.267275],"iteration":123,"passed_time":0.7522332353,"remaining_time":5.314163823},
{"learn":[52.20869766],"iteration":124,"passed_time":0.7580822354,"remaining_time":5.306575648},
{"learn":[52.13662316],"iteration":125,"passed_time":0.763984974,"remaining_time":5.299387836},
{"learn":[52.07769882],"iteration":126,"passed_time":0.7696488616,"remaining_time":5.290578395},
{"learn":[52.03143832],"iteration":127,"passed_time":0.7753571034,"remaining_time":5.282120267},
{"learn":[51.93466337],"iteration":128,"passed_time":0.7808122527,"remaining_time":5.271995907},
{"learn":[51.89657295],"iteration":129,"passed_time":0.7863907102,"remaining_time":5.262768599},
{"learn":[51.85613303],"iteration":130,"passed_time":0.7920614661,"remaining_time":5.254209267},
{"learn":[51.80372011],"iteration":131,"passed_time":0.7974616074,"remaining_time":5.243914206},
{"learn":[51.75561287],"iteration":132,"passed_time":0.8031404231,"remaining_time":5.235509375},
{"learn":[51.70171569],"iteration":133,"passed_time":0.8085616104,"remaining_time":5.225480258},
{"learn":[51.6554199],"iteration":134,"passed_time":0.8140219585,"remaining_time":5.215770327},
{"learn":[51.60238745],"iteration":135,"passed_time":0.8210237762,"remaining_time":5.215915755},
{"learn":[51.56263581],"iteration":136,"passed_time":0.826569066,"remaining_time":5.20678178},
{"learn":[51.50198569],"iteration":137,"passed_time":0.8337838795,"remaining_time":5.208128291},
{"learn":[51.42698761],"iteration":138,"passed_time":0.840194397,"remaining_time":5.20436961},
{"learn":[51.38148162],"iteration":139,"passed_time":0.8468731944,"remaining_time":5.202221051},
{"learn":[51.3462326],"iteration":140,"passed_time":0.8525338455,"remaining_time":5.193805484},
{"learn":[51.2942959],"iteration":141,"passed_time":0.8582998163,"remaining_time":5.186065087},
{"learn":[51.24161735],"iteration":142,"passed_time":0.8636923694,"remaining_time":5.17611441},
{"learn":[51.19510549],"iteration":143,"passed_time":0.8694054055,"remaining_time":5.168132132},
{"learn":[51.1551462],"iteration":144,"passed_time":0.8751415793,"remaining_time":5.160317588},
{"learn":[51.11008347],"iteration":145,"passed_time":0.8806305265,"remaining_time":5.151085408},
{"learn":[51.06960335],"iteration":146,"passed_time":0.8861193753,"remaining_time":5.141903586},
{"learn":[51.01152581],"iteration":147,"passed_time":0.891527766,"remaining_time":5.132308491},
{"learn":[50.9565046],"iteration":148,"passed_time":0.8979520529,"remaining_time":5.128571792},
{"learn":[50.90537209],"iteration":149,"passed_time":0.9032457482,"remaining_time":5.118392573},
{"learn":[50.84987096],"iteration":150,"passed_time":0.9086489952,"remaining_time":5.108894019},
{"learn":[50.79459775],"iteration":151,"passed_time":0.9145295283,"remaining_time":5.102112105},
{"learn":[50.75734796],"iteration":152,"passed_time":0.9196666523,"remaining_time":5.0912265},
{"learn":[50.71000888],"iteration":153,"passed_time":0.9252779824,"remaining_time":5.083020605},
{"learn":[50.6599554],"iteration":154,"passed_time":0.9307240955,"remaining_time":5.073947488},
{"learn":[50.60868876],"iteration":155,"passed_time":0.935978928,"remaining_time":5.063885995},
{"learn":[50.56608573],"iteration":156,"passed_time":0.9421124565,"remaining_time":5.058603827},
{"learn":[50.522689],"iteration":157,"passed_time":0.9491258265,"remaining_time":5.057999658},
{"learn":[50.46353217],"iteration":158,"passed_time":0.964843473,"remaining_time":5.10335447},
{"learn":[50.42923661],"iteration":159,"passed_time":0.9762014429,"remaining_time":5.125057575},
{"learn":[50.36195692],"iteration":160,"passed_time":0.983150006,"remaining_time":5.12337177},
{"learn":[50.3091012],"iteration":161,"passed_time":0.9902421633,"remaining_time":5.122363783},
{"learn":[50.25350278],"iteration":162,"passed_time":0.9974096687,"remaining_time":5.121668054},
{"learn":[50.20148919],"iteration":163,"passed_time":1.005276912,"remaining_time":5.124460354},
{"learn":[50.1629561],"iteration":164,"passed_time":1.012599065,"remaining_time":5.124364965},
{"learn":[50.11599373],"iteration":165,"passed_time":1.021646839,"remaining_time":5.132852192},
{"learn":[50.08536514],"iteration":166,"passed_time":1.028942447,"remaining_time":5.132389569},
{"learn":[50.03397551],"iteration":167,"passed_time":1.03656626,"remaining_time":5.133471},
{"learn":[49.99099812],"iteration":168,"passed_time":1.044688957,"remaining_time":5.136902504},
{"learn":[49.95914908],"iteration":169,"passed_time":1.054049583,"remaining_time":5.146242084},
{"learn":[49.90863105],"iteration":170,"passed_time":1.061527926,"remaining_time":5.146237725},
{"learn":[49.86900264],"iteration":171,"passed_time":1.067571363,"remaining_time":5.139238886},
{"learn":[49.82354091],"iteration":172,"passed_time":1.074918461,"remaining_time":5.138483048},
{"learn":[49.77946884],"iteration":173,"passed_time":1.081200386,"remaining_time":5.132594937},
{"learn":[49.75988553],"iteration":174,"passed_time":1.087699982,"remaining_time":5.127728487},
{"learn":[49.70211018],"iteration":175,"passed_time":1.093467693,"remaining_time":5.119416929},
{"learn":[49.67234495],"iteration":176,"passed_time":1.098660019,"remaining_time":5.108458733},
{"learn":[49.60992021],"iteration":177,"passed_time":1.104540315,"remaining_time":5.100742353},
{"learn":[49.57787266],"iteration":178,"passed_time":1.110104319,"remaining_time":5.091595785},
{"learn":[49.53573297],"iteration":179,"passed_time":1.11592386,"remaining_time":5.083653139},
{"learn":[49.50252205],"iteration":180,"passed_time":1.124294705,"remaining_time":5.087278249},
{"learn":[49.46371944],"iteration":181,"passed_time":1.130662954,"remaining_time":5.081770858},
{"learn":[49.43471301],"iteration":182,"passed_time":1.137255037,"remaining_time":5.077253362},
{"learn":[49.39540869],"iteration":183,"passed_time":1.143685319,"remaining_time":5.071995764},
{"learn":[49.36684044],"iteration":184,"passed_time":1.149462326,"remaining_time":5.063847543},
{"learn":[49.30088071],"iteration":185,"passed_time":1.156151506,"remaining_time":5.059716805},
{"learn":[49.27541607],"iteration":186,"passed_time":1.162537179,"remaining_time":5.054239177},
{"learn":[49.23907032],"iteration":187,"passed_time":1.16901975,"remaining_time":5.049170409},
{"learn":[49.21422215],"iteration":188,"passed_time":1.175484382,"remaining_time":5.044009704},
{"learn":[49.1624416],"iteration":189,"passed_time":1.184217529,"remaining_time":5.048506306},
{"learn":[49.12575278],"iteration":190,"passed_time":1.190109284,"remaining_time":5.040829374},
{"learn":[49.09536759],"iteration":191,"passed_time":1.196200651,"remaining_time":5.034011074},
{"learn":[49.06940836],"iteration":192,"passed_time":1.203457285,"remaining_time":5.032072688},
{"learn":[49.03486291],"iteration":193,"passed_time":1.208856221,"remaining_time":5.022361415},
{"learn":[48.99729072],"iteration":194,"passed_time":1.214859875,"remaining_time":5.015190768},
{"learn":[48.94923424],"iteration":195,"passed_time":1.220535336,"remaining_time":5.006685765},
{"learn":[48.91747503],"iteration":196,"passed_time":1.226588656,"remaining_time":4.999749701},
{"learn":[48.88158095],"iteration":197,"passed_time":1.232509859,"remaining_time":4.992287408},
{"learn":[48.85865899],"iteration":198,"passed_time":1.238362094,"remaining_time":4.984563},
{"learn":[48.84336097],"iteration":199,"passed_time":1.244830568,"remaining_time":4.979322272},
{"learn":[48.80342931],"iteration":200,"passed_time":1.251606228,"remaining_time":4.975290428},
{"learn":[48.76800399],"iteration":201,"passed_time":1.257284229,"remaining_time":4.966895123},
{"learn":[48.72603838],"iteration":202,"passed_time":1.262720918,"remaining_time":4.957579172},
{"learn":[48.69047376],"iteration":203,"passed_time":1.268601554,"remaining_time":4.950033514},
{"learn":[48.66339079],"iteration":204,"passed_time":1.276036202,"remaining_time":4.948530637},
{"learn":[48.63469875],"iteration":205,"passed_time":1.283372751,"remaining_time":4.946592061},
{"learn":[48.5778514],"iteration":206,"passed_time":1.289050483,"remaining_time":4.938246536},
{"learn":[48.52796817],"iteration":207,"passed_time":1.294750106,"remaining_time":4.930010019},
{"learn":[48.49517079],"iteration":208,"passed_time":1.300206319,"remaining_time":4.920876546},
{"learn":[48.47353054],"iteration":209,"passed_time":1.305469531,"remaining_time":4.911052045},
{"learn":[48.44958399],"iteration":210,"passed_time":1.311261217,"remaining_time":4.903246921},
{"learn":[48.41361769],"iteration":211,"passed_time":1.316504688,"remaining_time":4.893423085},
{"learn":[48.38457468],"iteration":212,"passed_time":1.3220281,"remaining_time":4.884676596},
{"learn":[48.3378421],"iteration":213,"passed_time":1.327683272,"remaining_time":4.876444168},
{"learn":[48.30771741],"iteration":214,"passed_time":1.333237527,"remaining_time":4.867867251},
{"learn":[48.28666222],"iteration":215,"passed_time":1.339117997,"remaining_time":4.86050236},
{"learn":[48.22320276],"iteration":216,"passed_time":1.344595002,"remaining_time":4.851695328},
{"learn":[48.19855591],"iteration":217,"passed_time":1.350596968,"remaining_time":4.844801969},
{"learn":[48.15516372],"iteration":218,"passed_time":1.358256211,"remaining_time":4.843826944},
{"learn":[48.11647033],"iteration":219,"passed_time":1.36456391,"remaining_time":4.837999317},
{"learn":[48.08926502],"iteration":220,"passed_time":1.369873329,"remaining_time":4.828648523},
{"learn":[48.05050556],"iteration":221,"passed_time":1.375540456,"remaining_time":4.820587725},
{"learn":[48.01947848],"iteration":222,"passed_time":1.381362223,"remaining_time":4.813087208},
{"learn":[47.98252199],"iteration":223,"passed_time":1.387002647,"remaining_time":4.804973454},
{"learn":[47.95111623],"iteration":224,"passed_time":1.392822499,"remaining_time":4.797499717},
{"learn":[47.90744469],"iteration":225,"passed_time":1.398498168,"remaining_time":4.789546822},
{"learn":[47.88719369],"iteration":226,"passed_time":1.404273885,"remaining_time":4.781954683},
{"learn":[47.85515658],"iteration":227,"passed_time":1.410013502,"remaining_time":4.774256244},
{"learn":[47.83413867],"iteration":228,"passed_time":1.415731761,"remaining_time":4.766503004},
{"learn":[47.80532303],"iteration":229,"passed_time":1.421161046,"remaining_time":4.757800022},
{"learn":[47.77647554],"iteration":230,"passed_time":1.426546631,"remaining_time":4.74897991},
{"learn":[47.7514927],"iteration":231,"passed_time":1.43217909,"remaining_time":4.741006643},
{"learn":[47.7248103],"iteration":232,"passed_time":1.439401649,"remaining_time":4.738287832},
{"learn":[47.69992844],"iteration":233,"passed_time":1.44641328,"remaining_time":4.734840054},
{"learn":[47.6452301],"iteration":234,"passed_time":1.477176602,"remaining_time":4.808681279},
{"learn":[47.61723037],"iteration":235,"passed_time":1.487327022,"remaining_time":4.814906123},
{"learn":[47.58195427],"iteration":236,"passed_time":1.49891258,"remaining_time":4.825613073},
{"learn":[47.56321353],"iteration":237,"passed_time":1.505137962,"remaining_time":4.818971123},
{"learn":[47.53989818],"iteration":238,"passed_time":1.512710208,"remaining_time":4.816621206},
{"learn":[47.52208021],"iteration":239,"passed_time":1.520376346,"remaining_time":4.814525095},
{"learn":[47.4953858],"iteration":240,"passed_time":1.526007748,"remaining_time":4.805974608},
{"learn":[47.45878068],"iteration":241,"passed_time":1.533102905,"remaining_time":4.802033067},
{"learn":[47.43051932],"iteration":242,"passed_time":1.538549006,"remaining_time":4.792928384},
{"learn":[47.40620786],"iteration":243,"passed_time":1.544213074,"remaining_time":4.784529033},
{"learn":[47.36562986],"iteration":244,"passed_time":1.549946049,"remaining_time":4.776364355},
{"learn":[47.3422522],"iteration":245,"passed_time":1.555337038,"remaining_time":4.767171246},
{"learn":[47.31231489],"iteration":246,"passed_time":1.560825199,"remaining_time":4.75830516},
{"learn":[47.29292453],"iteration":247,"passed_time":1.566683728,"remaining_time":4.750589368},
{"learn":[47.27180841],"iteration":248,"passed_time":1.5724277,"remaining_time":4.742542984},
{"learn":[47.24791121],"iteration":249,"passed_time":1.577974348,"remaining_time":4.733923044},
{"learn":[47.20838112],"iteration":250,"passed_time":1.583360057,"remaining_time":4.724847341},
{"learn":[47.17862387],"iteration":251,"passed_time":1.589585072,"remaining_time":4.718292197},
{"learn":[47.14935495],"iteration":252,"passed_time":1.595416432,"remaining_time":4.710577371},
{"learn":[47.10378691],"iteration":253,"passed_time":1.601309165,"remaining_time":4.703057627},
{"learn":[47.04666517],"iteration":254,"passed_time":1.607339986,"remaining_time":4.695954077},
{"learn":[47.01989044],"iteration":255,"passed_time":1.6128621,"remaining_time":4.687380478},
{"learn":[46.97321443],"iteration":256,"passed_time":1.618836171,"remaining_time":4.680137257},
{"learn":[46.94424869],"iteration":257,"passed_time":1.624263546,"remaining_time":4.671331595},
{"learn":[46.92061768],"iteration":258,"passed_time":1.629960181,"remaining_time":4.663322372},
{"learn":[46.9052767],"iteration":259,"passed_time":1.635436213,"remaining_time":4.654703068},
{"learn":[46.85224226],"iteration":260,"passed_time":1.640932884,"remaining_time":4.646166288},
{"learn":[46.84000718],"iteration":261,"passed_time":1.646427295,"remaining_time":4.63764635},
{"learn":[46.82024249],"iteration":262,"passed_time":1.65177294,"remaining_time":4.628732535},
{"learn":[46.79833146],"iteration":263,"passed_time":1.657478058,"remaining_time":4.62084792},
{"learn":[46.76673163],"iteration":264,"passed_time":1.663555124,"remaining_time":4.614011382},
{"learn":[46.71911153],"iteration":265,"passed_time":1.670199011,"remaining_time":4.608744639},
{"learn":[46.70620447],"iteration":266,"passed_time":1.675680527,"remaining_time":4.600276502},
{"learn":[46.66207108],"iteration":267,"passed_time":1.681155411,"remaining_time":4.591812542},
{"learn":[46.63658572],"iteration":268,"passed_time":1.68675666,"remaining_time":4.583714196},
{"learn":[46.6039135],"iteration":269,"passed_time":1.692579077,"remaining_time":4.57623232},
{"learn":[46.57784244],"iteration":270,"passed_time":1.698388355,"remaining_time":4.568727346},
{"learn":[46.52403928],"iteration":271,"passed_time":1.703862333,"remaining_time":4.560337421},
{"learn":[46.48173262],"iteration":272,"passed_time":1.709559252,"remaining_time":4.55256255},
{"learn":[46.44035223],"iteration":273,"passed_time":1.715376759,"remaining_time":4.545122362},
{"learn":[46.41931647],"iteration":274,"passed_time":1.720776511,"remaining_time":4.536592621},
{"learn":[46.38021898],"iteration":275,"passed_time":1.726628684,"remaining_time":4.529272345},
{"learn":[46.32338518],"iteration":276,"passed_time":1.732443656,"remaining_time":4.521865571},
{"learn":[46.29844857],"iteration":277,"passed_time":1.737972276,"remaining_time":4.513726558},
{"learn":[46.25931367],"iteration":278,"passed_time":1.743877951,"remaining_time":4.506580654},
{"learn":[46.23443941],"iteration":279,"passed_time":1.749451131,"remaining_time":4.498588621},
{"learn":[46.20801803],"iteration":280,"passed_time":1.755309928,"remaining_time":4.491344621},
{"learn":[46.19195002],"iteration":281,"passed_time":1.760421428,"remaining_time":4.48220775},
{"learn":[46.16006086],"iteration":282,"passed_time":1.765924806,"remaining_time":4.474092177},
{"learn":[46.11701876],"iteration":283,"passed_time":1.771791016,"remaining_time":4.466909744},
{"learn":[46.09879774],"iteration":284,"passed_time":1.777574029,"remaining_time":4.459527827},
{"learn":[46.076685],"iteration":285,"passed_time":1.783210453,"remaining_time":4.451791132},
{"learn":[46.05101921],"iteration":286,"passed_time":1.788626119,"remaining_time":4.443520637},
{"learn":[46.01772725],"iteration":287,"passed_time":1.794997107,"remaining_time":4.437631737},
{"learn":[45.99730275],"iteration":288,"passed_time":1.801424452,"remaining_time":4.431878149},
{"learn":[45.96399334],"iteration":289,"passed_time":1.807769243,"remaining_time":4.425917801},
{"learn":[45.92995375],"iteration":290,"passed_time":1.813032464,"remaining_time":4.417319646},
{"learn":[45.91432059],"iteration":291,"passed_time":1.818376725,"remaining_time":4.408940827},
{"learn":[45.88375278],"iteration":292,"passed_time":1.824800739,"remaining_time":4.403188132},
{"learn":[45.85943468],"iteration":293,"passed_time":1.830316113,"remaining_time":4.395248897},
{"learn":[45.83656179],"iteration":294,"passed_time":1.835454945,"remaining_time":4.386426224},
{"learn":[45.81807613],"iteration":295,"passed_time":1.841178528,"remaining_time":4.379019201},
{"learn":[45.78970001],"iteration":296,"passed_time":1.846607327,"remaining_time":4.37092576},
{"learn":[45.75430897],"iteration":297,"passed_time":1.851635668,"remaining_time":4.361906843},
{"learn":[45.73562984],"iteration":298,"passed_time":1.857208721,"remaining_time":4.354191684},
{"learn":[45.7089561],"iteration":299,"passed_time":1.862808404,"remaining_time":4.346552942},
{"learn":[45.68276319],"iteration":300,"passed_time":1.868139961,"remaining_time":4.338305093},
{"learn":[45.6525155],"iteration":301,"passed_time":1.873755521,"remaining_time":4.330732959},
{"learn":[45.63604697],"iteration":302,"passed_time":1.879488786,"remaining_time":4.323444501},
{"learn":[45.61679021],"iteration":303,"passed_time":1.884894778,"remaining_time":4.315416991},
{"learn":[45.59793746],"iteration":304,"passed_time":1.890484272,"remaining_time":4.307824817},
{"learn":[45.54659146],"iteration":305,"passed_time":1.8963081,"remaining_time":4.300777194},
{"learn":[45.52282175],"iteration":306,"passed_time":1.902605943,"remaining_time":4.294807551},
{"learn":[45.49917171],"iteration":307,"passed_time":1.908435588,"remaining_time":4.287783853},
{"learn":[45.46794216],"iteration":308,"passed_time":1.914333531,"remaining_time":4.280920614},
{"learn":[45.42138042],"iteration":309,"passed_time":1.920120508,"remaining_time":4.273816615},
{"learn":[45.38219545],"iteration":310,"passed_time":1.926339429,"remaining_time":4.267678029},
{"learn":[45.35441259],"iteration":311,"passed_time":1.93191914,"remaining_time":4.260129387},
{"learn":[45.33770566],"iteration":312,"passed_time":1.937321456,"remaining_time":4.252203962},
{"learn":[45.30471328],"iteration":313,"passed_time":1.94315422,"remaining_time":4.245235016},
{"learn":[45.28265149],"iteration":314,"passed_time":1.949627316,"remaining_time":4.239665751},
{"learn":[45.22679054],"iteration":315,"passed_time":1.967058656,"remaining_time":4.257810508},
{"learn":[45.20504211],"iteration":316,"passed_time":1.973968291,"remaining_time":4.253061019},
{"learn":[45.14832601],"iteration":317,"passed_time":1.981158881,"remaining_time":4.248900494},
{"learn":[45.12952632],"iteration":318,"passed_time":1.986710034,"remaining_time":4.241221107},
{"learn":[45.09510087],"iteration":319,"passed_time":1.992601659,"remaining_time":4.234278525},
{"learn":[45.05232651],"iteration":320,"passed_time":1.998329191,"remaining_time":4.226995391},
{"learn":[45.02931627],"iteration":321,"passed_time":2.004186179,"remaining_time":4.219994501},
{"learn":[45.01813036],"iteration":322,"passed_time":2.009825049,"remaining_time":4.212543523},
{"learn":[44.99774437],"iteration":323,"passed_time":2.015899232,"remaining_time":4.206011978},
{"learn":[44.97756719],"iteration":324,"passed_time":2.022042518,"remaining_time":4.199626767},
{"learn":[44.94579458],"iteration":325,"passed_time":2.027540363,"remaining_time":4.191908603},
{"learn":[44.91175296],"iteration":326,"passed_time":2.033850746,"remaining_time":4.185876306},
{"learn":[44.87775118],"iteration":327,"passed_time":2.039486088,"remaining_time":4.178459302},
{"learn":[44.8447852],"iteration":328,"passed_time":2.046316247,"remaining_time":4.173489974},
{"learn":[44.80112857],"iteration":329,"passed_time":2.055700978,"remaining_time":4.173695925},
{"learn":[44.76857009],"iteration":330,"passed_time":2.061275265,"remaining_time":4.166142453},
{"learn":[44.73756361],"iteration":331,"passed_time":2.068161067,"remaining_time":4.161239738},
{"learn":[44.71736491],"iteration":332,"passed_time":2.077141567,"remaining_time":4.160520797},
{"learn":[44.67261918],"iteration":333,"passed_time":2.120508813,"remaining_time":4.228319969},
{"learn":[44.63471606],"iteration":334,"passed_time":2.191527923,"remaining_time":4.350346473},
{"learn":[44.60665024],"iteration":335,"passed_time":2.207267202,"remaining_time":4.361980424},
{"learn":[44.58431817],"iteration":336,"passed_time":2.212828392,"remaining_time":4.353427964},
{"learn":[44.55630866],"iteration":337,"passed_time":2.220074592,"remaining_time":4.348193432},
{"learn":[44.52701204],"iteration":338,"passed_time":2.226001649,"remaining_time":4.340374896},
{"learn":[44.49883887],"iteration":339,"passed_time":2.232830534,"remaining_time":4.334318095},
{"learn":[44.47880334],"iteration":340,"passed_time":2.238772055,"remaining_time":4.326541888},
{"learn":[44.45943763],"iteration":341,"passed_time":2.24661191,"remaining_time":4.322428763},
{"learn":[44.44238935],"iteration":342,"passed_time":2.252872053,"remaining_time":4.315268043},
{"learn":[44.42525376],"iteration":343,"passed_time":2.258938484,"remaining_time":4.307743155},
{"learn":[44.40470896],"iteration":344,"passed_time":2.265432227,"remaining_time":4.301037997},
{"learn":[44.38017556],"iteration":345,"passed_time":2.271198641,"remaining_time":4.292959281},
{"learn":[44.35305316],"iteration":346,"passed_time":2.276802249,"remaining_time":4.284587518},
{"learn":[44.33986904],"iteration":347,"passed_time":2.284548264,"remaining_time":4.280245598},
{"learn":[44.31387553],"iteration":348,"passed_time":2.290777226,"remaining_time":4.273054367},
{"learn":[44.27618062],"iteration":349,"passed_time":2.296421075,"remaining_time":4.264781996},
{"learn":[44.24897623],"iteration":350,"passed_time":2.302615752,"remaining_time":4.257543086},
{"learn":[44.21846782],"iteration":351,"passed_time":2.30808398,"remaining_time":4.248972782},
{"learn":[44.18904277],"iteration":352,"passed_time":2.314225013,"remaining_time":4.24165321},
{"learn":[44.14804391],"iteration":353,"passed_time":2.319528802,"remaining_time":4.232812447},
{"learn":[44.10448078],"iteration":354,"passed_time":2.325124729,"remaining_time":4.224522396},
{"learn":[44.07878666],"iteration":355,"passed_time":2.331090842,"remaining_time":4.216917142},
{"learn":[44.04739205],"iteration":356,"passed_time":2.336558939,"remaining_time":4.208424083},
{"learn":[44.01900752],"iteration":357,"passed_time":2.341912938,"remaining_time":4.199743314},
{"learn":[43.97974312],"iteration":358,"passed_time":2.347484177,"remaining_time":4.191468962},
{"learn":[43.96250149],"iteration":359,"passed_time":2.352913731,"remaining_time":4.182957744},
{"learn":[43.94489924],"iteration":360,"passed_time":2.358489379,"remaining_time":4.174722198},
{"learn":[43.90293945],"iteration":361,"passed_time":2.365523174,"remaining_time":4.16907123},
{"learn":[43.87778784],"iteration":362,"passed_time":2.370780088,"remaining_time":4.160294535},
{"learn":[43.8470245],"iteration":363,"passed_time":2.376713469,"remaining_time":4.152719138},
{"learn":[43.81294449],"iteration":364,"passed_time":2.38344966,"remaining_time":4.146549408},
{"learn":[43.79150177],"iteration":365,"passed_time":2.390195464,"remaining_time":4.140393235},
{"learn":[43.76612043],"iteration":366,"passed_time":2.397002168,"remaining_time":4.134338889},
{"learn":[43.74736622],"iteration":367,"passed_time":2.403192502,"remaining_time":4.127221905},
{"learn":[43.72643435],"iteration":368,"passed_time":2.409492272,"remaining_time":4.120297083},
{"learn":[43.69431313],"iteration":369,"passed_time":2.416270887,"remaining_time":4.11419097},
{"learn":[43.66881321],"iteration":370,"passed_time":2.422939711,"remaining_time":4.107895089},
{"learn":[43.64627337],"iteration":371,"passed_time":2.431488636,"remaining_time":4.104771139},
{"learn":[43.60410457],"iteration":372,"passed_time":2.437793319,"remaining_time":4.097845605},
{"learn":[43.56712181],"iteration":373,"passed_time":2.444316797,"remaining_time":4.091289612},
{"learn":[43.54577929],"iteration":374,"passed_time":2.449668077,"remaining_time":4.082780128},
{"learn":[43.51910928],"iteration":375,"passed_time":2.455383931,"remaining_time":4.074892481},
{"learn":[43.50241638],"iteration":376,"passed_time":2.460988508,"remaining_time":4.066832469},
{"learn":[43.47086327],"iteration":377,"passed_time":2.466551246,"remaining_time":4.0587166},
{"learn":[43.45030465],"iteration":378,"passed_time":2.472127225,"remaining_time":4.050635902},
{"learn":[43.42608423],"iteration":379,"passed_time":2.477641617,"remaining_time":4.042467901},
{"learn":[43.40737844],"iteration":380,"passed_time":2.482861438,"remaining_time":4.033835249},
{"learn":[43.36999121],"iteration":381,"passed_time":2.48868694,"remaining_time":4.026200337},
{"learn":[43.34218999],"iteration":382,"passed_time":2.494217785,"remaining_time":4.018100192},
{"learn":[43.31306342],"iteration":383,"passed_time":2.499645173,"remaining_time":4.009847465},
{"learn":[43.2784531],"iteration":384,"passed_time":2.505321995,"remaining_time":4.002007862},
{"learn":[43.25290442],"iteration":385,"passed_time":2.51152057,"remaining_time":3.995009404},
{"learn":[43.21453184],"iteration":386,"passed_time":2.517315043,"remaining_time":3.987374991},
{"learn":[43.19146151],"iteration":387,"passed_time":2.522857079,"remaining_time":3.979351887},
{"learn":[43.1681121],"iteration":388,"passed_time":2.528701896,"remaining_time":3.971817116},
{"learn":[43.13774741],"iteration":389,"passed_time":2.534327902,"remaining_time":3.963948769},
{"learn":[43.11046295],"iteration":390,"passed_time":2.539667233,"remaining_time":3.955645383},
{"learn":[43.08518199],"iteration":391,"passed_time":2.545745859,"remaining_time":3.948503781},
{"learn":[43.06076453],"iteration":392,"passed_time":2.551430464,"remaining_time":3.940759012},
{"learn":[43.02031682],"iteration":393,"passed_time":2.557175448,"remaining_time":3.933117568},
{"learn":[42.97197397],"iteration":394,"passed_time":2.562945123,"remaining_time":3.925523542},
{"learn":[42.95018193],"iteration":395,"passed_time":2.567972723,"remaining_time":3.91680688},
{"learn":[42.93240832],"iteration":396,"passed_time":2.575213424,"remaining_time":3.911470264},
{"learn":[42.91444366],"iteration":397,"passed_time":2.581839378,"remaining_time":3.905194235},
{"learn":[42.88746797],"iteration":398,"passed_time":2.590959266,"remaining_time":3.90267298},
{"learn":[42.86476215],"iteration":399,"passed_time":2.599021563,"remaining_time":3.898532345},
{"learn":[42.84423103],"iteration":400,"passed_time":2.606828152,"remaining_time":3.893990182},
{"learn":[42.8157054],"iteration":401,"passed_time":2.612997114,"remaining_time":3.886995707},
{"learn":[42.78156416],"iteration":402,"passed_time":2.619613332,"remaining_time":3.880667889},
{"learn":[42.75953002],"iteration":403,"passed_time":2.625600538,"remaining_time":3.873410695},
{"learn":[42.73221373],"iteration":404,"passed_time":2.633304515,"remaining_time":3.868681942},
{"learn":[42.71337891],"iteration":405,"passed_time":2.644634105,"remaining_time":3.869243001},
{"learn":[42.68046983],"iteration":406,"passed_time":2.653068594,"remaining_time":3.86552746},
{"learn":[42.66448236],"iteration":407,"passed_time":2.659630463,"remaining_time":3.859071652},
{"learn":[42.63135318],"iteration":408,"passed_time":2.667209694,"remaining_time":3.854085402},
{"learn":[42.58892759],"iteration":409,"passed_time":2.67619903,"remaining_time":3.851115677},
{"learn":[42.56208714],"iteration":410,"passed_time":2.684832804,"remaining_time":3.847607109},
{"learn":[42.5334703],"iteration":411,"passed_time":2.695559201,"remaining_time":3.847060218},
{"learn":[42.51525139],"iteration":412,"passed_time":2.701680161,"remaining_time":3.839918292},
{"learn":[42.48664526],"iteration":413,"passed_time":2.70717296,"remaining_time":3.831892161},
{"learn":[42.45974985],"iteration":414,"passed_time":2.712478761,"remaining_time":3.823614639},
{"learn":[42.41845306],"iteration":415,"passed_time":2.718268907,"remaining_time":3.816031351},
{"learn":[42.37135794],"iteration":416,"passed_time":2.723817723,"remaining_time":3.808119262},
{"learn":[42.35077003],"iteration":417,"passed_time":2.729278782,"remaining_time":3.800096294},
{"learn":[42.32749227],"iteration":418,"passed_time":2.734828035,"remaining_time":3.792207847},
{"learn":[42.29707861],"iteration":419,"passed_time":2.741083315,"remaining_time":3.785305531},
{"learn":[42.2519745],"iteration":420,"passed_time":2.746771228,"remaining_time":3.777625988},
{"learn":[42.22035036],"iteration":421,"passed_time":2.752457416,"remaining_time":3.769953522},
{"learn":[42.19379285],"iteration":422,"passed_time":2.758236638,"remaining_time":3.762417353},
{"learn":[42.15179494],"iteration":423,"passed_time":2.763980112,"remaining_time":3.754840906},
{"learn":[42.13646841],"iteration":424,"passed_time":2.769194047,"remaining_time":3.746556652},
{"learn":[42.12487363],"iteration":425,"passed_time":2.774714,"remaining_time":3.738699146},
{"learn":[42.10986895],"iteration":426,"passed_time":2.801728321,"remaining_time":3.759696318},
{"learn":[42.09537966],"iteration":427,"passed_time":2.811341045,"remaining_time":3.757212799},
{"learn":[42.06686652],"iteration":428,"passed_time":2.817363104,"remaining_time":3.749916859},
{"learn":[42.03712403],"iteration":429,"passed_time":2.823476013,"remaining_time":3.742747273},
{"learn":[42.01722244],"iteration":430,"passed_time":2.828954585,"remaining_time":3.734745148},
{"learn":[41.98724264],"iteration":431,"passed_time":2.834442325,"remaining_time":3.726766761},
{"learn":[41.96749723],"iteration":432,"passed_time":2.840139433,"remaining_time":3.719074037},
{"learn":[41.92754035],"iteration":433,"passed_time":2.845735357,"remaining_time":3.711258554},
{"learn":[41.90612293],"iteration":434,"passed_time":2.851916794,"remaining_time":3.704213767},
{"learn":[41.88628103],"iteration":435,"passed_time":2.857355003,"remaining_time":3.696211518},
{"learn":[41.83737841],"iteration":436,"passed_time":2.863072482,"remaining_time":3.688580794},
{"learn":[41.80488828],"iteration":437,"passed_time":2.86882052,"remaining_time":3.680998019},
{"learn":[41.77810056],"iteration":438,"passed_time":2.874604177,"remaining_time":3.673469119},
{"learn":[41.75093273],"iteration":439,"passed_time":2.879980511,"remaining_time":3.665429742},
{"learn":[41.72722514],"iteration":440,"passed_time":2.885422362,"remaining_time":3.657485488},
{"learn":[41.70430807],"iteration":441,"passed_time":2.890859311,"remaining_time":3.64954637},
{"learn":[41.69602867],"iteration":442,"passed_time":2.899095806,"remaining_time":3.645138519},
{"learn":[41.6693953],"iteration":443,"passed_time":2.907350913,"remaining_time":3.640736729},
{"learn":[41.65615254],"iteration":444,"passed_time":2.915395043,"remaining_time":3.636054492},
{"learn":[41.63507476],"iteration":445,"passed_time":2.92333286,"remaining_time":3.631225122},
{"learn":[41.61595997],"iteration":446,"passed_time":2.931731361,"remaining_time":3.626951773},
{"learn":[41.60196277],"iteration":447,"passed_time":2.93832465,"remaining_time":3.620435729},
{"learn":[41.58308515],"iteration":448,"passed_time":2.945074157,"remaining_time":3.614111048},
{"learn":[41.56062307],"iteration":449,"passed_time":2.95158372,"remaining_time":3.607491213},
{"learn":[41.54345426],"iteration":450,"passed_time":2.957707901,"remaining_time":3.600402745},
{"learn":[41.52448366],"iteration":451,"passed_time":2.966121806,"remaining_time":3.596094579},
{"learn":[41.50371537],"iteration":452,"passed_time":2.994600582,"remaining_time":3.61599673},
{"learn":[41.46562023],"iteration":453,"passed_time":3.001123584,"remaining_time":3.609280786},
{"learn":[41.44106681],"iteration":454,"passed_time":3.007861409,"remaining_time":3.602823006},
{"learn":[41.42835992],"iteration":455,"passed_time":3.013289508,"remaining_time":3.594801518},
{"learn":[41.40095161],"iteration":456,"passed_time":3.018881427,"remaining_time":3.586986029},
{"learn":[41.37421333],"iteration":457,"passed_time":3.024460069,"remaining_time":3.579164536},
{"learn":[41.3540033],"iteration":458,"passed_time":3.029980075,"remaining_time":3.571283705},
{"learn":[41.34492698],"iteration":459,"passed_time":3.035120469,"remaining_time":3.562967507},
{"learn":[41.31733997],"iteration":460,"passed_time":3.040634391,"remaining_time":3.555101815},
{"learn":[41.29403752],"iteration":461,"passed_time":3.04633535,"remaining_time":3.547464108},
{"learn":[41.27517309],"iteration":462,"passed_time":3.05261602,"remaining_time":3.540507134},
{"learn":[41.24939549],"iteration":463,"passed_time":3.058444782,"remaining_time":3.533031042},
{"learn":[41.2288512],"iteration":464,"passed_time":3.064067371,"remaining_time":3.525324825},
{"learn":[41.18924413],"iteration":465,"passed_time":3.069710742,"remaining_time":3.517651365},
{"learn":[41.17490348],"iteration":466,"passed_time":3.075172428,"remaining_time":3.509779238},
{"learn":[41.1574039],"iteration":467,"passed_time":3.08075441,"remaining_time":3.502054158},
{"learn":[41.13222115],"iteration":468,"passed_time":3.086182973,"remaining_time":3.494164518},
{"learn":[41.11696998],"iteration":469,"passed_time":3.091809517,"remaining_time":3.486508604},
{"learn":[41.09494235],"iteration":470,"passed_time":3.097658937,"remaining_time":3.47911163},
{"learn":[41.07079618],"iteration":471,"passed_time":3.103271875,"remaining_time":3.471456674},
{"learn":[41.04388238],"iteration":472,"passed_time":3.109031702,"remaining_time":3.463974011},
{"learn":[41.01635351],"iteration":473,"passed_time":3.115039582,"remaining_time":3.456773882},
{"learn":[41.00142217],"iteration":474,"passed_time":3.12092021,"remaining_time":3.449438127},
{"learn":[40.96338521],"iteration":475,"passed_time":3.12728754,"remaining_time":3.442644267},
{"learn":[40.95214262],"iteration":476,"passed_time":3.134347015,"remaining_time":3.436611087},
{"learn":[40.93597825],"iteration":477,"passed_time":3.140339895,"remaining_time":3.429408839},
{"learn":[40.91554101],"iteration":478,"passed_time":3.146547168,"remaining_time":3.422444832},
{"learn":[40.89205851],"iteration":479,"passed_time":3.153000204,"remaining_time":3.415750221},
{"learn":[40.85832368],"iteration":480,"passed_time":3.159223726,"remaining_time":3.408808969},
{"learn":[40.8455453],"iteration":481,"passed_time":3.165552554,"remaining_time":3.401983865},
{"learn":[40.81545514],"iteration":482,"passed_time":3.171658448,"remaining_time":3.39492219},
{"learn":[40.7927157],"iteration":483,"passed_time":3.177656319,"remaining_time":3.387749298},
{"learn":[40.77298419],"iteration":484,"passed_time":3.183756619,"remaining_time":3.380690018},
{"learn":[40.7414797],"iteration":485,"passed_time":3.189676461,"remaining_time":3.373443829},
{"learn":[40.7053641],"iteration":486,"passed_time":3.195912348,"remaining_time":3.366536005},
{"learn":[40.67326228],"iteration":487,"passed_time":3.202198025,"remaining_time":3.359683174},
{"learn":[40.63377974],"iteration":488,"passed_time":3.209402991,"remaining_time":3.35379331},
{"learn":[40.611377],"iteration":489,"passed_time":3.216732593,"remaining_time":3.348027801},
{"learn":[40.58664088],"iteration":490,"passed_time":3.224979821,"remaining_time":3.343207187},
{"learn":[40.56999724],"iteration":491,"passed_time":3.231592568,"remaining_time":3.336685009},
{"learn":[40.54601995],"iteration":492,"passed_time":3.237676653,"remaining_time":3.329618789},
{"learn":[40.50376941],"iteration":493,"passed_time":3.243833819,"remaining_time":3.322631401},
{"learn":[40.48621659],"iteration":494,"passed_time":3.249946983,"remaining_time":3.315602478},
{"learn":[40.46756669],"iteration":495,"passed_time":3.256031126,"remaining_time":3.308547757},
{"learn":[40.44633579],"iteration":496,"passed_time":3.262452205,"remaining_time":3.301837946},
{"learn":[40.41349945],"iteration":497,"passed_time":3.268687271,"remaining_time":3.294941787},
{"learn":[40.39312793],"iteration":498,"passed_time":3.274901332,"remaining_time":3.288027189},
{"learn":[40.37301047],"iteration":499,"passed_time":3.282076356,"remaining_time":3.282076356},
{"learn":[40.3524675],"iteration":500,"passed_time":3.289255127,"remaining_time":3.276124368},
{"learn":[40.33895646],"iteration":501,"passed_time":3.295360484,"remaining_time":3.269102631},
{"learn":[40.31644544],"iteration":502,"passed_time":3.301500648,"remaining_time":3.26211893},
{"learn":[40.29869771],"iteration":503,"passed_time":3.307609917,"remaining_time":3.255108173},
{"learn":[40.28201795],"iteration":504,"passed_time":3.314035421,"remaining_time":3.248410957},
{"learn":[40.27130919],"iteration":505,"passed_time":3.320151976,"remaining_time":3.241413194},
{"learn":[40.25185285],"iteration":506,"passed_time":3.3263342,"remaining_time":3.234482762},
{"learn":[40.23022213],"iteration":507,"passed_time":3.332652681,"remaining_time":3.227687242},
{"learn":[40.2029054],"iteration":508,"passed_time":3.338775726,"remaining_time":3.220705071},
{"learn":[40.18593126],"iteration":509,"passed_time":3.344735797,"remaining_time":3.213569688},
{"learn":[40.1640889],"iteration":510,"passed_time":3.350940861,"remaining_time":3.206673349},
{"learn":[40.15175395],"iteration":511,"passed_time":3.356326224,"remaining_time":3.198998433},
{"learn":[40.12373438],"iteration":512,"passed_time":3.362100644,"remaining_time":3.191701781},
{"learn":[40.11029289],"iteration":513,"passed_time":3.368813261,"remaining_time":3.185298142},
{"learn":[40.08374449],"iteration":514,"passed_time":3.374358881,"remaining_time":3.177794286},
{"learn":[40.06899921],"iteration":515,"passed_time":3.380005489,"remaining_time":3.170392745},
{"learn":[40.03511916],"iteration":516,"passed_time":3.385380804,"remaining_time":3.162744542},
{"learn":[40.00935141],"iteration":517,"passed_time":3.391184677,"remaining_time":3.155503888},
{"learn":[39.97750288],"iteration":518,"passed_time":3.397167847,"remaining_time":3.148434941},
{"learn":[39.96142944],"iteration":519,"passed_time":3.403043738,"remaining_time":3.141271143},
{"learn":[39.94430694],"iteration":520,"passed_time":3.409766435,"remaining_time":3.13489083},
{"learn":[39.92922957],"iteration":521,"passed_time":3.416021959,"remaining_time":3.128081411},
{"learn":[39.90756995],"iteration":522,"passed_time":3.422387208,"remaining_time":3.121374184},
{"learn":[39.88090793],"iteration":523,"passed_time":3.429058223,"remaining_time":3.114946019},
{"learn":[39.86202208],"iteration":524,"passed_time":3.43580392,"remaining_time":3.108584499},
{"learn":[39.84920546],"iteration":525,"passed_time":3.443586295,"remaining_time":3.103155711},
{"learn":[39.83297503],"iteration":526,"passed_time":3.450838056,"remaining_time":3.097241747},
{"learn":[39.81880871],"iteration":527,"passed_time":3.456909556,"remaining_time":3.090267633},
{"learn":[39.79957573],"iteration":528,"passed_time":3.462864034,"remaining_time":3.083192741},
{"learn":[39.77208124],"iteration":529,"passed_time":3.468563238,"remaining_time":3.075895702},
{"learn":[39.7553193],"iteration":530,"passed_time":3.474280116,"remaining_time":3.068620291},
{"learn":[39.73365516],"iteration":531,"passed_time":3.479952304,"remaining_time":3.061311425},
{"learn":[39.72226929],"iteration":532,"passed_time":3.4855803,"remaining_time":3.053969982},
{"learn":[39.70281966],"iteration":533,"passed_time":3.491241506,"remaining_time":3.046663936},
{"learn":[39.69467421],"iteration":534,"passed_time":3.497140397,"remaining_time":3.039570626},
{"learn":[39.6673131],"iteration":535,"passed_time":3.502577489,"remaining_time":3.032082006},
{"learn":[39.64855649],"iteration":536,"passed_time":3.508370949,"remaining_time":3.024908285},
{"learn":[39.63758202],"iteration":537,"passed_time":3.514070796,"remaining_time":3.017659308},
{"learn":[39.62478093],"iteration":538,"passed_time":3.520540127,"remaining_time":3.011074209},
{"learn":[39.61185078],"iteration":539,"passed_time":3.526195114,"remaining_time":3.003795838},
{"learn":[39.59524796],"iteration":540,"passed_time":3.531590576,"remaining_time":2.99630328},
{"learn":[39.58207527],"iteration":541,"passed_time":3.537229458,"remaining_time":2.989024155},
{"learn":[39.54877275],"iteration":542,"passed_time":3.543121871,"remaining_time":2.981964448},
{"learn":[39.53393932],"iteration":543,"passed_time":3.548544048,"remaining_time":2.974514864},
{"learn":[39.51729393],"iteration":544,"passed_time":3.553972986,"remaining_time":2.967078364},
{"learn":[39.49164458],"iteration":545,"passed_time":3.559435516,"remaining_time":2.959677151},
{"learn":[39.46838272],"iteration":546,"passed_time":3.564999397,"remaining_time":2.95236696},
{"learn":[39.45334006],"iteration":547,"passed_time":3.570949403,"remaining_time":2.945381624},
{"learn":[39.42871241],"iteration":548,"passed_time":3.576338391,"remaining_time":2.937939188},
{"learn":[39.40073941],"iteration":549,"passed_time":3.581941534,"remaining_time":2.930679437},
{"learn":[39.39253016],"iteration":550,"passed_time":3.587376714,"remaining_time":2.923288829},
{"learn":[39.36979685],"iteration":551,"passed_time":3.593179081,"remaining_time":2.916203312},
{"learn":[39.34008155],"iteration":552,"passed_time":3.599933191,"remaining_time":2.909891748},
{"learn":[39.31149246],"iteration":553,"passed_time":3.605665986,"remaining_time":2.902756371},
{"learn":[39.29447767],"iteration":554,"passed_time":3.611107472,"remaining_time":2.895392478},
{"learn":[39.25679998],"iteration":555,"passed_time":3.617120189,"remaining_time":2.888491661},
{"learn":[39.23957117],"iteration":556,"passed_time":3.623213904,"remaining_time":2.881658455},
{"learn":[39.21075173],"iteration":557,"passed_time":3.628669458,"remaining_time":2.874322402},
{"learn":[39.19047504],"iteration":558,"passed_time":3.634173869,"remaining_time":2.867031621},
{"learn":[39.17747725],"iteration":559,"passed_time":3.639590027,"remaining_time":2.859677879},
{"learn":[39.16591302],"iteration":560,"passed_time":3.64485153,"remaining_time":2.852210021},
{"learn":[39.15296291],"iteration":561,"passed_time":3.650423331,"remaining_time":2.844991848},
{"learn":[39.13972873],"iteration":562,"passed_time":3.656391822,"remaining_time":2.838087435},
{"learn":[39.11038208],"iteration":563,"passed_time":3.661830387,"remaining_time":2.830776682},
{"learn":[39.07671459],"iteration":564,"passed_time":3.667820129,"remaining_time":2.823896913},
{"learn":[39.04808533],"iteration":565,"passed_time":3.673782207,"remaining_time":2.816999078},
{"learn":[39.03283657],"iteration":566,"passed_time":3.680102241,"remaining_time":2.810377902},
{"learn":[39.00540208],"iteration":567,"passed_time":3.685697444,"remaining_time":2.803206507},
{"learn":[38.96435764],"iteration":568,"passed_time":3.691226205,"remaining_time":2.795990324},
{"learn":[38.94498608],"iteration":569,"passed_time":3.697214291,"remaining_time":2.789126571},
{"learn":[38.93329095],"iteration":570,"passed_time":3.702821642,"remaining_time":2.781979833},
{"learn":[38.91681567],"iteration":571,"passed_time":3.708221388,"remaining_time":2.774683136},
{"learn":[38.90095998],"iteration":572,"passed_time":3.713547839,"remaining_time":2.767338442},
{"learn":[38.87418893],"iteration":573,"passed_time":3.7193282,"remaining_time":2.760337654},
{"learn":[38.86242885],"iteration":574,"passed_time":3.724577025,"remaining_time":2.752948236},
{"learn":[38.85089272],"iteration":575,"passed_time":3.730132297,"remaining_time":2.74579183},
{"learn":[38.82919667],"iteration":576,"passed_time":3.73563553,"remaining_time":2.738602824},
{"learn":[38.81033781],"iteration":577,"passed_time":3.741145104,"remaining_time":2.73142428},
{"learn":[38.78356719],"iteration":578,"passed_time":3.746556616,"remaining_time":2.7241802},
{"learn":[38.76944683],"iteration":579,"passed_time":3.752268079,"remaining_time":2.717159643},
{"learn":[38.75450629],"iteration":580,"passed_time":3.758172422,"remaining_time":2.710282693},
{"learn":[38.73396898],"iteration":581,"passed_time":3.763467051,"remaining_time":2.702971181},
{"learn":[38.71414296],"iteration":582,"passed_time":3.770081923,"remaining_time":2.696610912},
{"learn":[38.69740751],"iteration":583,"passed_time":3.777474023,"remaining_time":2.690803414},
{"learn":[38.68437331],"iteration":584,"passed_time":3.782682799,"remaining_time":2.683441644},
{"learn":[38.66887362],"iteration":585,"passed_time":3.788293859,"remaining_time":2.676371429},
{"learn":[38.65281655],"iteration":586,"passed_time":3.793903322,"remaining_time":2.669305063},
{"learn":[38.64003318],"iteration":587,"passed_time":3.799312171,"remaining_time":2.662103086},
{"learn":[38.61891709],"iteration":588,"passed_time":3.804847136,"remaining_time":2.6549952},
{"learn":[38.61035822],"iteration":589,"passed_time":3.810533721,"remaining_time":2.64799801},
{"learn":[38.59528134],"iteration":590,"passed_time":3.815636314,"remaining_time":2.640601104},
{"learn":[38.58174343],"iteration":591,"passed_time":3.821360833,"remaining_time":2.633640574},
{"learn":[38.54635854],"iteration":592,"passed_time":3.827268965,"remaining_time":2.626810234},
{"learn":[38.53508957],"iteration":593,"passed_time":3.833659773,"remaining_time":2.620312909},
{"learn":[38.5174194],"iteration":594,"passed_time":3.839296382,"remaining_time":2.613302579},
{"learn":[38.49993385],"iteration":595,"passed_time":3.84470934,"remaining_time":2.606145257},
{"learn":[38.4627642],"iteration":596,"passed_time":3.850215994,"remaining_time":2.599057027},
{"learn":[38.447852],"iteration":597,"passed_time":3.855518115,"remaining_time":2.591836592},
{"learn":[38.42785376],"iteration":598,"passed_time":3.86121389,"remaining_time":2.584886093},
{"learn":[38.41037015],"iteration":599,"passed_time":3.866942816,"remaining_time":2.577961877},
{"learn":[38.3954329],"iteration":600,"passed_time":3.872649729,"remaining_time":2.571027025},
{"learn":[38.38448972],"iteration":601,"passed_time":3.878077245,"remaining_time":2.563911534},
{"learn":[38.35660772],"iteration":602,"passed_time":3.883706701,"remaining_time":2.556934594},
{"learn":[38.34133062],"iteration":603,"passed_time":3.889308773,"remaining_time":2.549944162},
{"learn":[38.32740469],"iteration":604,"passed_time":3.895136764,"remaining_time":2.543105821},
{"learn":[38.30999398],"iteration":605,"passed_time":3.900795036,"remaining_time":2.536160469},
{"learn":[38.27340938],"iteration":606,"passed_time":3.907117474,"remaining_time":2.529649369},
{"learn":[38.26032546],"iteration":607,"passed_time":3.91261562,"remaining_time":2.522607439},
{"learn":[38.24790978],"iteration":608,"passed_time":3.918197911,"remaining_time":2.515624603},
{"learn":[38.21978497],"iteration":609,"passed_time":3.923533225,"remaining_time":2.508488455},
{"learn":[38.21170639],"iteration":610,"passed_time":3.928929935,"remaining_time":2.501397291},
{"learn":[38.1897586],"iteration":611,"passed_time":3.934428534,"remaining_time":2.49437626},
{"learn":[38.17100204],"iteration":612,"passed_time":3.93981347,"remaining_time":2.487288438},
{"learn":[38.15178119],"iteration":613,"passed_time":3.945050694,"remaining_time":2.480113303},
{"learn":[38.13806919],"iteration":614,"passed_time":3.950480749,"remaining_time":2.473065184},
{"learn":[38.11859427],"iteration":615,"passed_time":3.955987989,"remaining_time":2.466070435},
{"learn":[38.11083058],"iteration":616,"passed_time":3.961646578,"remaining_time":2.459174456},
{"learn":[38.09890413],"iteration":617,"passed_time":3.967405349,"remaining_time":2.452344407},
{"learn":[38.08774801],"iteration":618,"passed_time":3.97336207,"remaining_time":2.445639658},
{"learn":[38.0644629],"iteration":619,"passed_time":3.979058601,"remaining_time":2.438777852},
{"learn":[38.05208366],"iteration":620,"passed_time":3.986529336,"remaining_time":2.433002606},
{"learn":[38.0396165],"iteration":621,"passed_time":3.992914337,"remaining_time":2.426562089},
{"learn":[38.02715742],"iteration":622,"passed_time":4.021415747,"remaining_time":2.433505195},
{"learn":[38.00881739],"iteration":623,"passed_time":4.02756555,"remaining_time":2.426866421},
{"learn":[37.98031154],"iteration":624,"passed_time":4.035428329,"remaining_time":2.421256997},
{"learn":[37.96944974],"iteration":625,"passed_time":4.041255064,"remaining_time":2.414423952},
{"learn":[37.9522608],"iteration":626,"passed_time":4.047104414,"remaining_time":2.40760757},
{"learn":[37.92331425],"iteration":627,"passed_time":4.052644818,"remaining_time":2.400611261},
{"learn":[37.90534038],"iteration":628,"passed_time":4.057989505,"remaining_time":2.393504144},
{"learn":[37.89201369],"iteration":629,"passed_time":4.064259067,"remaining_time":2.386945801},
{"learn":[37.86749011],"iteration":630,"passed_time":4.069722843,"remaining_time":2.379917162},
{"learn":[37.8521102],"iteration":631,"passed_time":4.07521775,"remaining_time":2.372911601},
{"learn":[37.84094608],"iteration":632,"passed_time":4.080796055,"remaining_time":2.365959166},
{"learn":[37.81508512],"iteration":633,"passed_time":4.08702297,"remaining_time":2.3593855},
{"learn":[37.79414799],"iteration":634,"passed_time":4.092787126,"remaining_time":2.352546931},
{"learn":[37.7751372],"iteration":635,"passed_time":4.098462607,"remaining_time":2.345660989},
{"learn":[37.75826532],"iteration":636,"passed_time":4.104026779,"remaining_time":2.338715417},
{"learn":[37.72575397],"iteration":637,"passed_time":4.109585729,"remaining_time":2.331771213},
{"learn":[37.6998573],"iteration":638,"passed_time":4.115642815,"remaining_time":2.325112764},
{"learn":[37.6737179],"iteration":639,"passed_time":4.121186957,"remaining_time":2.318167663},
{"learn":[37.66064778],"iteration":640,"passed_time":4.126478823,"remaining_time":2.311085643},
{"learn":[37.64421609],"iteration":641,"passed_time":4.131936114,"remaining_time":2.304101447},
{"learn":[37.62841921],"iteration":642,"passed_time":4.137293932,"remaining_time":2.297066771},
{"learn":[37.61921948],"iteration":643,"passed_time":4.143636536,"remaining_time":2.290581687},
{"learn":[37.60177406],"iteration":644,"passed_time":4.149522989,"remaining_time":2.283845986},
{"learn":[37.58715483],"iteration":645,"passed_time":4.154949231,"remaining_time":2.276860724},
{"learn":[37.57366386],"iteration":646,"passed_time":4.160697386,"remaining_time":2.270055915},
{"learn":[37.54168068],"iteration":647,"passed_time":4.16645361,"remaining_time":2.263258751},
{"learn":[37.52803092],"iteration":648,"passed_time":4.172288431,"remaining_time":2.256507302},
{"learn":[37.50836165],"iteration":649,"passed_time":4.177883192,"remaining_time":2.249629411},
{"learn":[37.4853423],"iteration":650,"passed_time":4.183391917,"remaining_time":2.242709338},
{"learn":[37.46342893],"iteration":651,"passed_time":4.189749067,"remaining_time":2.236246434},
{"learn":[37.44170783],"iteration":652,"passed_time":4.196446997,"remaining_time":2.229964943},
{"learn":[37.41488346],"iteration":653,"passed_time":4.202023375,"remaining_time":2.223088819},
{"learn":[37.39560026],"iteration":654,"passed_time":4.207303413,"remaining_time":2.216060576},
{"learn":[37.38154457],"iteration":655,"passed_time":4.212661678,"remaining_time":2.209078685},
{"learn":[37.36520142],"iteration":656,"passed_time":4.218295636,"remaining_time":2.202245667},
{"learn":[37.3577201],"iteration":657,"passed_time":4.223995057,"remaining_time":2.195450318},
{"learn":[37.33789165],"iteration":658,"passed_time":4.229667244,"remaining_time":2.188644204},
{"learn":[37.33016311],"iteration":659,"passed_time":4.234941654,"remaining_time":2.181636609},
{"learn":[37.31441997],"iteration":660,"passed_time":4.240528208,"remaining_time":2.174794346},
{"learn":[37.30234847],"iteration":661,"passed_time":4.246262503,"remaining_time":2.168031308},
{"learn":[37.29139966],"iteration":662,"passed_time":4.251739271,"remaining_time":2.161140474},
{"learn":[37.27904423],"iteration":663,"passed_time":4.257272175,"remaining_time":2.154282305},
{"learn":[37.25958268],"iteration":664,"passed_time":4.263278694,"remaining_time":2.147666711},
{"learn":[37.23967145],"iteration":665,"passed_time":4.268865519,"remaining_time":2.140842467},
{"learn":[37.22323456],"iteration":666,"passed_time":4.274560241,"remaining_time":2.134075802},
{"learn":[37.20253933],"iteration":667,"passed_time":4.279924844,"remaining_time":2.127148276},
{"learn":[37.19478159],"iteration":668,"passed_time":4.28570471,"remaining_time":2.12043088},
{"learn":[37.17689485],"iteration":669,"passed_time":4.291484397,"remaining_time":2.113716195},
{"learn":[37.16201227],"iteration":670,"passed_time":4.297471035,"remaining_time":2.107105768},
{"learn":[37.14256603],"iteration":671,"passed_time":4.303208195,"remaining_time":2.100375428},
{"learn":[37.12273194],"iteration":672,"passed_time":4.309008388,"remaining_time":2.093678667},
{"learn":[37.10251112],"iteration":673,"passed_time":4.314853628,"remaining_time":2.087006354},
{"learn":[37.06701619],"iteration":674,"passed_time":4.320418719,"remaining_time":2.080201606},
{"learn":[37.05788151],"iteration":675,"passed_time":4.326168221,"remaining_time":2.073488911},
{"learn":[37.04504932],"iteration":676,"passed_time":4.33178512,"remaining_time":2.066715796},
{"learn":[37.02883234],"iteration":677,"passed_time":4.337522179,"remaining_time":2.060003159},
{"learn":[37.01659174],"iteration":678,"passed_time":4.342983369,"remaining_time":2.053162977},
{"learn":[36.99121051],"iteration":679,"passed_time":4.348687656,"remaining_time":2.04644125},
{"learn":[36.98194025],"iteration":680,"passed_time":4.354293295,"remaining_time":2.039676301},
{"learn":[36.97089926],"iteration":681,"passed_time":4.360019495,"remaining_time":2.032970967},
{"learn":[36.95398699],"iteration":682,"passed_time":4.36558378,"remaining_time":2.026193351},
{"learn":[36.92515458],"iteration":683,"passed_time":4.371658692,"remaining_time":2.019655185},
{"learn":[36.91287805],"iteration":684,"passed_time":4.377771653,"remaining_time":2.01313587},
{"learn":[36.89468683],"iteration":685,"passed_time":4.383335055,"remaining_time":2.006366191},
{"learn":[36.88071005],"iteration":686,"passed_time":4.388983296,"remaining_time":1.999638678},
{"learn":[36.87410748],"iteration":687,"passed_time":4.394667631,"remaining_time":1.99293067},
{"learn":[36.86572519],"iteration":688,"passed_time":4.400289632,"remaining_time":1.986197497},
{"learn":[36.83281278],"iteration":689,"passed_time":4.405925251,"remaining_time":1.979473663},
{"learn":[36.81543848],"iteration":690,"passed_time":4.41181097,"remaining_time":1.972864819},
{"learn":[36.79613522],"iteration":691,"passed_time":4.417426033,"remaining_time":1.966137598},
{"learn":[36.77215268],"iteration":692,"passed_time":4.423142906,"remaining_time":1.95945869},
{"learn":[36.74968247],"iteration":693,"passed_time":4.428921091,"remaining_time":1.952809588},
{"learn":[36.73326169],"iteration":694,"passed_time":4.43513724,"remaining_time":1.946355191},
{"learn":[36.71957055],"iteration":695,"passed_time":4.441912385,"remaining_time":1.94014564},
{"learn":[36.70112016],"iteration":696,"passed_time":4.449791681,"remaining_time":1.934414461},
{"learn":[36.68260268],"iteration":697,"passed_time":4.456575102,"remaining_time":1.928202981},
{"learn":[36.65809949],"iteration":698,"passed_time":4.462793176,"remaining_time":1.921746418},
{"learn":[36.63302564],"iteration":699,"passed_time":4.46906584,"remaining_time":1.915313931},
{"learn":[36.61343155],"iteration":700,"passed_time":4.477467141,"remaining_time":1.909789836},
{"learn":[36.59866797],"iteration":701,"passed_time":4.483031096,"remaining_time":1.903053086},
{"learn":[36.58523384],"iteration":702,"passed_time":4.48918883,"remaining_time":1.89657053},
{"learn":[36.56686535],"iteration":703,"passed_time":4.494662684,"remaining_time":1.889801356},
{"learn":[36.54990154],"iteration":704,"passed_time":4.500143417,"remaining_time":1.883038735},
{"learn":[36.53870969],"iteration":705,"passed_time":4.506061289,"remaining_time":1.876461783},
{"learn":[36.52897427],"iteration":706,"passed_time":4.51171335,"remaining_time":1.869776537},
{"learn":[36.50613824],"iteration":707,"passed_time":4.517482981,"remaining_time":1.863142699},
{"learn":[36.49559552],"iteration":708,"passed_time":4.524144779,"remaining_time":1.856877476},
{"learn":[36.4821831],"iteration":709,"passed_time":4.531257341,"remaining_time":1.850795252},
{"learn":[36.47083418],"iteration":710,"passed_time":4.539120037,"remaining_time":1.845015036},
{"learn":[36.4609763],"iteration":711,"passed_time":4.547271272,"remaining_time":1.839345683},
{"learn":[36.45055123],"iteration":712,"passed_time":4.555200785,"remaining_time":1.833580119},
{"learn":[36.43324969],"iteration":713,"passed_time":4.56312677,"remaining_time":1.827807081},
{"learn":[36.41407555],"iteration":714,"passed_time":4.569362334,"remaining_time":1.821354217},
{"learn":[36.39978341],"iteration":715,"passed_time":4.57472778,"remaining_time":1.814556829},
{"learn":[36.38675437],"iteration":716,"passed_time":4.580114714,"remaining_time":1.807771917},
{"learn":[36.37943144],"iteration":717,"passed_time":4.585519191,"remaining_time":1.800997788},
{"learn":[36.36422993],"iteration":718,"passed_time":4.591196842,"remaining_time":1.794334232},
{"learn":[36.34908744],"iteration":719,"passed_time":4.596889852,"remaining_time":1.787679387},
{"learn":[36.33688628],"iteration":720,"passed_time":4.603296852,"remaining_time":1.781303498},
{"learn":[36.32044516],"iteration":721,"passed_time":4.608734939,"remaining_time":1.77455445},
{"learn":[36.30395051],"iteration":722,"passed_time":4.615243873,"remaining_time":1.768219299},
{"learn":[36.29509364],"iteration":723,"passed_time":4.621210922,"remaining_time":1.761677092},
{"learn":[36.28852344],"iteration":724,"passed_time":4.626676212,"remaining_time":1.754946149},
{"learn":[36.2612709],"iteration":725,"passed_time":4.632228442,"remaining_time":1.748251506},
{"learn":[36.24614197],"iteration":726,"passed_time":4.637589384,"remaining_time":1.741488173},
{"learn":[36.22886676],"iteration":727,"passed_time":4.6434598,"remaining_time":1.734919046},
{"learn":[36.21334915],"iteration":728,"passed_time":4.649196358,"remaining_time":1.728302075},
{"learn":[36.19523069],"iteration":729,"passed_time":4.654773161,"remaining_time":1.72162843},
{"learn":[36.16799911],"iteration":730,"passed_time":4.660317817,"remaining_time":1.714945954},
{"learn":[36.1480243],"iteration":731,"passed_time":4.665580746,"remaining_time":1.708163443},
{"learn":[36.13096703],"iteration":732,"passed_time":4.670901902,"remaining_time":1.701406286},
{"learn":[36.1179973],"iteration":733,"passed_time":4.676574496,"remaining_time":1.694780403},
{"learn":[36.09458839],"iteration":734,"passed_time":4.683075826,"remaining_time":1.68845591},
{"learn":[36.0846006],"iteration":735,"passed_time":4.688413199,"remaining_time":1.68171343},
{"learn":[36.06968631],"iteration":736,"passed_time":4.693851407,"remaining_time":1.675010746},
{"learn":[36.06000937],"iteration":737,"passed_time":4.699441269,"remaining_time":1.668365329},
{"learn":[36.05042853],"iteration":738,"passed_time":4.704924083,"remaining_time":1.66168496},
{"learn":[36.04079238],"iteration":739,"passed_time":4.710740423,"remaining_time":1.655125014},
{"learn":[36.03071828],"iteration":740,"passed_time":4.716195168,"remaining_time":1.648440686},
{"learn":[36.01158523],"iteration":741,"passed_time":4.721875887,"remaining_time":1.641838247},
{"learn":[35.99770861],"iteration":742,"passed_time":4.727854237,"remaining_time":1.635341237},
{"learn":[35.98372982],"iteration":743,"passed_time":4.733557182,"remaining_time":1.628750858},
{"learn":[35.97938026],"iteration":744,"passed_time":4.738962761,"remaining_time":1.622061079},
{"learn":[35.95570186],"iteration":745,"passed_time":4.744687198,"remaining_time":1.615483309},
{"learn":[35.94229585],"iteration":746,"passed_time":4.75016114,"remaining_time":1.608822983},
{"learn":[35.9260671],"iteration":747,"passed_time":4.758399317,"remaining_time":1.603097096},
{"learn":[35.9181088],"iteration":748,"passed_time":4.766771662,"remaining_time":1.597409462},
{"learn":[35.90089208],"iteration":749,"passed_time":4.774896815,"remaining_time":1.591632272},
{"learn":[35.88546396],"iteration":750,"passed_time":4.784915843,"remaining_time":1.586476758},
{"learn":[35.8700984],"iteration":751,"passed_time":4.793853612,"remaining_time":1.580951723},
{"learn":[35.85360793],"iteration":752,"passed_time":4.802229553,"remaining_time":1.575233333},
{"learn":[35.84333972],"iteration":753,"passed_time":4.810281787,"remaining_time":1.569402281},
{"learn":[35.81322949],"iteration":754,"passed_time":4.820113558,"remaining_time":1.56414281},
{"learn":[35.80417977],"iteration":755,"passed_time":4.828263754,"remaining_time":1.558328513},
{"learn":[35.79100134],"iteration":756,"passed_time":4.839735889,"remaining_time":1.5535744},
{"learn":[35.76869319],"iteration":757,"passed_time":4.850407928,"remaining_time":1.548547122},
{"learn":[35.75133937],"iteration":758,"passed_time":4.859078109,"remaining_time":1.542869334},
{"learn":[35.74076438],"iteration":759,"passed_time":4.867288625,"remaining_time":1.537038513},
{"learn":[35.72417283],"iteration":760,"passed_time":4.87589122,"remaining_time":1.531324575},
{"learn":[35.70743549],"iteration":761,"passed_time":4.885066476,"remaining_time":1.525781918},
{"learn":[35.6748422],"iteration":762,"passed_time":4.893092107,"remaining_time":1.519872647},
{"learn":[35.66671902],"iteration":763,"passed_time":4.90166986,"remaining_time":1.514128386},
{"learn":[35.64480638],"iteration":764,"passed_time":4.910636622,"remaining_time":1.508496217},
{"learn":[35.63773827],"iteration":765,"passed_time":4.920882014,"remaining_time":1.503245942},
{"learn":[35.61437804],"iteration":766,"passed_time":4.929431529,"remaining_time":1.497467466},
{"learn":[35.60064111],"iteration":767,"passed_time":4.938379774,"remaining_time":1.491802224},
{"learn":[35.57932758],"iteration":768,"passed_time":4.949026608,"remaining_time":1.486638682},
{"learn":[35.5707161],"iteration":769,"passed_time":4.957175206,"remaining_time":1.480714672},
{"learn":[35.5555841],"iteration":770,"passed_time":4.965536105,"remaining_time":1.474847948},
{"learn":[35.5365099],"iteration":771,"passed_time":4.971759723,"remaining_time":1.468343545},
{"learn":[35.51825903],"iteration":772,"passed_time":4.979279781,"remaining_time":1.462220583},
{"learn":[35.50151507],"iteration":773,"passed_time":4.985452274,"remaining_time":1.455700535},
{"learn":[35.4875786],"iteration":774,"passed_time":4.992280288,"remaining_time":1.449371696},
{"learn":[35.47297862],"iteration":775,"passed_time":4.999013282,"remaining_time":1.443014143},
{"learn":[35.46032983],"iteration":776,"passed_time":5.004711451,"remaining_time":1.436358627},
{"learn":[35.44803356],"iteration":777,"passed_time":5.010616332,"remaining_time":1.429764557},
{"learn":[35.43405736],"iteration":778,"passed_time":5.02054783,"remaining_time":1.424314596},
{"learn":[35.41591438],"iteration":779,"passed_time":5.028678595,"remaining_time":1.418345245},
{"learn":[35.39653836],"iteration":780,"passed_time":5.064401504,"remaining_time":1.420107464},
{"learn":[35.38323376],"iteration":781,"passed_time":5.077639828,"remaining_time":1.415505732},
{"learn":[35.36850028],"iteration":782,"passed_time":5.085760273,"remaining_time":1.409463575},
{"learn":[35.34220872],"iteration":783,"passed_time":5.092748365,"remaining_time":1.403104141},
{"learn":[35.33326054],"iteration":784,"passed_time":5.100561837,"remaining_time":1.396969166},
{"learn":[35.3249843],"iteration":785,"passed_time":5.106644134,"remaining_time":1.390358581},
{"learn":[35.30895594],"iteration":786,"passed_time":5.113482831,"remaining_time":1.383954057},
{"learn":[35.29128047],"iteration":787,"passed_time":5.119559256,"remaining_time":1.377343353},
{"learn":[35.28261896],"iteration":788,"passed_time":5.12503513,"remaining_time":1.3705734},
{"learn":[35.27207333],"iteration":789,"passed_time":5.130644355,"remaining_time":1.36384217},
{"learn":[35.25529428],"iteration":790,"passed_time":5.135952328,"remaining_time":1.35703418},
{"learn":[35.24601721],"iteration":791,"passed_time":5.142406456,"remaining_time":1.350530989},
{"learn":[35.22972638],"iteration":792,"passed_time":5.148036657,"remaining_time":1.343812847},
{"learn":[35.22262338],"iteration":793,"passed_time":5.153167339,"remaining_time":1.336967849},
{"learn":[35.20911327],"iteration":794,"passed_time":5.158833462,"remaining_time":1.330265232},
{"learn":[35.19931379],"iteration":795,"passed_time":5.164418001,"remaining_time":1.323544312},
{"learn":[35.18790782],"iteration":796,"passed_time":5.169715723,"remaining_time":1.316753189},
{"learn":[35.17634826],"iteration":797,"passed_time":5.175462839,"remaining_time":1.310079566},
{"learn":[35.16317351],"iteration":798,"passed_time":5.180804529,"remaining_time":1.303306271},
{"learn":[35.15727472],"iteration":799,"passed_time":5.186562159,"remaining_time":1.29664054},
{"learn":[35.1420608],"iteration":800,"passed_time":5.192143445,"remaining_time":1.289933265},
{"learn":[35.12683472],"iteration":801,"passed_time":5.197978302,"remaining_time":1.283291401},
{"learn":[35.11220422],"iteration":802,"passed_time":5.203890476,"remaining_time":1.276670515},
{"learn":[35.10348649],"iteration":803,"passed_time":5.20941244,"remaining_time":1.269956266},
{"learn":[35.08219484],"iteration":804,"passed_time":5.215187062,"remaining_time":1.263306183},
{"learn":[35.07471399],"iteration":805,"passed_time":5.221562539,"remaining_time":1.256802894},
{"learn":[35.05795085],"iteration":806,"passed_time":5.227307267,"remaining_time":1.250149074},
{"learn":[35.04246777],"iteration":807,"passed_time":5.233695289,"remaining_time":1.243650366},
{"learn":[35.02404031],"iteration":808,"passed_time":5.240121216,"remaining_time":1.23716088},
{"learn":[35.0157369],"iteration":809,"passed_time":5.246871094,"remaining_time":1.230747541},
{"learn":[35.00643195],"iteration":810,"passed_time":5.252487607,"remaining_time":1.224069245},
{"learn":[34.9874722],"iteration":811,"passed_time":5.259481851,"remaining_time":1.217712547},
{"learn":[34.97403662],"iteration":812,"passed_time":5.265501572,"remaining_time":1.211130128},
{"learn":[34.95054958],"iteration":813,"passed_time":5.271967234,"remaining_time":1.204650989},
{"learn":[34.93041966],"iteration":814,"passed_time":5.278615768,"remaining_time":1.198213395},
{"learn":[34.91842656],"iteration":815,"passed_time":5.284851197,"remaining_time":1.191682133},
{"learn":[34.90035905],"iteration":816,"passed_time":5.291783427,"remaining_time":1.185307671},
{"learn":[34.89090315],"iteration":817,"passed_time":5.29867396,"remaining_time":1.178922568},
{"learn":[34.87707667],"iteration":818,"passed_time":5.305413571,"remaining_time":1.172502877},
{"learn":[34.85428722],"iteration":819,"passed_time":5.313966829,"remaining_time":1.166480523},
{"learn":[34.83803108],"iteration":820,"passed_time":5.320245326,"remaining_time":1.159956045},
{"learn":[34.8271894],"iteration":821,"passed_time":5.328054515,"remaining_time":1.15376363},
{"learn":[34.8187229],"iteration":822,"passed_time":5.334374313,"remaining_time":1.147246966},
{"learn":[34.79557996],"iteration":823,"passed_time":5.342766627,"remaining_time":1.141173454},
{"learn":[34.78356562],"iteration":824,"passed_time":5.348528701,"remaining_time":1.134536391},
{"learn":[34.76656838],"iteration":825,"passed_time":5.354881362,"remaining_time":1.128025856},
{"learn":[34.75158145],"iteration":826,"passed_time":5.36067953,"remaining_time":1.121399708},
{"learn":[34.74022209],"iteration":827,"passed_time":5.366584005,"remaining_time":1.114797643},
{"learn":[34.72924382],"iteration":828,"passed_time":5.376401678,"remaining_time":1.109004448},
{"learn":[34.71815069],"iteration":829,"passed_time":5.382358357,"remaining_time":1.102410748},
{"learn":[34.71101054],"iteration":830,"passed_time":5.389219633,"remaining_time":1.096002549},
{"learn":[34.68934498],"iteration":831,"passed_time":5.395468889,"remaining_time":1.08946968},
{"learn":[34.68277027],"iteration":832,"passed_time":5.400950524,"remaining_time":1.082783598},
{"learn":[34.66150544],"iteration":833,"passed_time":5.407133958,"remaining_time":1.076240092},
{"learn":[34.64105068],"iteration":834,"passed_time":5.41308065,"remaining_time":1.069650667},
{"learn":[34.61416394],"iteration":835,"passed_time":5.419638007,"remaining_time":1.063182576},
{"learn":[34.59630397],"iteration":836,"passed_time":5.425001192,"remaining_time":1.056481714},
{"learn":[34.58999897],"iteration":837,"passed_time":5.431164322,"remaining_time":1.049938688},
{"learn":[34.57889034],"iteration":838,"passed_time":5.437680681,"remaining_time":1.04346435},
{"learn":[34.56581869],"iteration":839,"passed_time":5.443458355,"remaining_time":1.03684921},
{"learn":[34.55052403],"iteration":840,"passed_time":5.450845132,"remaining_time":1.030540281},
{"learn":[34.53406656],"iteration":841,"passed_time":5.457860495,"remaining_time":1.024159095},
{"learn":[34.52411377],"iteration":842,"passed_time":5.463741607,"remaining_time":1.017565163},
{"learn":[34.50234589],"iteration":843,"passed_time":5.469944144,"remaining_time":1.01103233},
{"learn":[34.493695],"iteration":844,"passed_time":5.475687826,"remaining_time":1.00441611},
{"learn":[34.48250062],"iteration":845,"passed_time":5.483512162,"remaining_time":0.9981807009},
{"learn":[34.4698571],"iteration":846,"passed_time":5.491385331,"remaining_time":0.9919503608},
{"learn":[34.45003885],"iteration":847,"passed_time":5.497811716,"remaining_time":0.9854568171},
{"learn":[34.43468607],"iteration":848,"passed_time":5.504733966,"remaining_time":0.9790516241},
{"learn":[34.41583833],"iteration":849,"passed_time":5.511328584,"remaining_time":0.9725873971},
{"learn":[34.40289583],"iteration":850,"passed_time":5.517969712,"remaining_time":0.9661310071},
{"learn":[34.38004918],"iteration":851,"passed_time":5.527747017,"remaining_time":0.9602189655},
{"learn":[34.36557219],"iteration":852,"passed_time":5.533497692,"remaining_time":0.9536039399},
{"learn":[34.35203121],"iteration":853,"passed_time":5.540310449,"remaining_time":0.9471725124},
{"learn":[34.34417663],"iteration":854,"passed_time":5.545915371,"remaining_time":0.9405353554},
{"learn":[34.33824515],"iteration":855,"passed_time":5.551870637,"remaining_time":0.9339595464},
{"learn":[34.32993535],"iteration":856,"passed_time":5.558073604,"remaining_time":0.9274265174},
{"learn":[34.32650302],"iteration":857,"passed_time":5.564073522,"remaining_time":0.9208606528},
{"learn":[34.31998308],"iteration":858,"passed_time":5.570418143,"remaining_time":0.914352687},
{"learn":[34.299807],"iteration":859,"passed_time":5.576145489,"remaining_time":0.9077446145},
{"learn":[34.28988511],"iteration":860,"passed_time":5.582207806,"remaining_time":0.9011926656},
{"learn":[34.27203509],"iteration":861,"passed_time":5.588787507,"remaining_time":0.8947246821},
{"learn":[34.26344153],"iteration":862,"passed_time":5.594983248,"remaining_time":0.8881954867},
{"learn":[34.25264356],"iteration":863,"passed_time":5.603417053,"remaining_time":0.8820193509},
{"learn":[34.24149691],"iteration":864,"passed_time":5.609403006,"remaining_time":0.8754559604},
{"learn":[34.23493564],"iteration":865,"passed_time":5.615548058,"remaining_time":0.8689185217},
{"learn":[34.22200926],"iteration":866,"passed_time":5.621054762,"remaining_time":0.8622840639},
{"learn":[34.19322043],"iteration":867,"passed_time":5.626709255,"remaining_time":0.8556746793},
{"learn":[34.18136777],"iteration":868,"passed_time":5.632660577,"remaining_time":0.8491122388},
{"learn":[34.16755286],"iteration":869,"passed_time":5.63867459,"remaining_time":0.8425605709},
{"learn":[34.15517471],"iteration":870,"passed_time":5.644588889,"remaining_time":0.8359953693},
{"learn":[34.14468512],"iteration":871,"passed_time":5.651092883,"remaining_time":0.8295182214},
{"learn":[34.12587513],"iteration":872,"passed_time":5.656739063,"remaining_time":0.8229162211},
{"learn":[34.11793448],"iteration":873,"passed_time":5.662527315,"remaining_time":0.8163368898},
{"learn":[34.10411648],"iteration":874,"passed_time":5.668509243,"remaining_time":0.8097870347},
{"learn":[34.08628142],"iteration":875,"passed_time":5.674350519,"remaining_time":0.8032185666},
{"learn":[34.07840713],"iteration":876,"passed_time":5.680929667,"remaining_time":0.7967552441},
{"learn":[34.0676133],"iteration":877,"passed_time":5.686549274,"remaining_time":0.7901583274},
{"learn":[34.0501445],"iteration":878,"passed_time":5.692143678,"remaining_time":0.7835601651},
{"learn":[34.03328809],"iteration":879,"passed_time":5.698312653,"remaining_time":0.7770426345},
{"learn":[34.01243617],"iteration":880,"passed_time":5.703917517,"remaining_time":0.7704496987},
{"learn":[33.99899164],"iteration":881,"passed_time":5.709627051,"remaining_time":0.7638730069},
{"learn":[33.98022676],"iteration":882,"passed_time":5.715446272,"remaining_time":0.757312813},
{"learn":[33.96478373],"iteration":883,"passed_time":5.720934794,"remaining_time":0.7507109006},
{"learn":[33.94237145],"iteration":884,"passed_time":5.726864481,"remaining_time":0.7441688309},
{"learn":[33.92450222],"iteration":885,"passed_time":5.73255902,"remaining_time":0.7375978875},
{"learn":[33.90708593],"iteration":886,"passed_time":5.738859575,"remaining_time":0.731106124},
{"learn":[33.88895453],"iteration":887,"passed_time":5.744619296,"remaining_time":0.7245465779},
{"learn":[33.86955341],"iteration":888,"passed_time":5.75061616,"remaining_time":0.7180184406},
{"learn":[33.85058084],"iteration":889,"passed_time":5.757276036,"remaining_time":0.7115734427},
{"learn":[33.8381299],"iteration":890,"passed_time":5.763698096,"remaining_time":0.7050988692},
{"learn":[33.82653148],"iteration":891,"passed_time":5.769750141,"remaining_time":0.6985796135},
{"learn":[33.82066342],"iteration":892,"passed_time":5.775011897,"remaining_time":0.691966711},
{"learn":[33.80918089],"iteration":893,"passed_time":5.781095675,"remaining_time":0.6854542971},
{"learn":[33.79300053],"iteration":894,"passed_time":5.78680661,"remaining_time":0.6788990995},
{"learn":[33.78032142],"iteration":895,"passed_time":5.792308048,"remaining_time":0.6723214699},
{"learn":[33.75897398],"iteration":896,"passed_time":5.79888384,"remaining_time":0.6658696049},
{"learn":[33.74260388],"iteration":897,"passed_time":5.804498992,"remaining_time":0.6593083488},
{"learn":[33.73229413],"iteration":898,"passed_time":5.809637488,"remaining_time":0.6526956466},
{"learn":[33.72235576],"iteration":899,"passed_time":5.816034443,"remaining_time":0.6462260492},
{"learn":[33.7050998],"iteration":900,"passed_time":5.822455882,"remaining_time":0.6397593034},
{"learn":[33.69773205],"iteration":901,"passed_time":5.829689763,"remaining_time":0.6333809277},
{"learn":[33.68603776],"iteration":902,"passed_time":5.835904835,"remaining_time":0.626891217},
{"learn":[33.67721319],"iteration":903,"passed_time":5.841490905,"remaining_time":0.6203353173},
{"learn":[33.66864798],"iteration":904,"passed_time":5.848062329,"remaining_time":0.6138849958},
{"learn":[33.66230283],"iteration":905,"passed_time":5.854209556,"remaining_time":0.6073903955},
{"learn":[33.64255256],"iteration":906,"passed_time":5.860168538,"remaining_time":0.6008772591},
{"learn":[33.6337481],"iteration":907,"passed_time":5.866331071,"remaining_time":0.5943859675},
{"learn":[33.62571294],"iteration":908,"passed_time":5.871809848,"remaining_time":0.5878269485},
{"learn":[33.61458856],"iteration":909,"passed_time":5.878099089,"remaining_time":0.5813504593},
{"learn":[33.60251191],"iteration":910,"passed_time":5.884013218,"remaining_time":0.5748377348},
{"learn":[33.58775395],"iteration":911,"passed_time":5.889754615,"remaining_time":0.5683096559},
{"learn":[33.5835435],"iteration":912,"passed_time":5.896678767,"remaining_time":0.5618960051},
{"learn":[33.56713997],"iteration":913,"passed_time":5.903128665,"remaining_time":0.555436614},
{"learn":[33.56025793],"iteration":914,"passed_time":5.910530288,"remaining_time":0.5490656551},
{"learn":[33.55023063],"iteration":915,"passed_time":5.915985441,"remaining_time":0.5425139487},
{"learn":[33.53936752],"iteration":916,"passed_time":5.921570796,"remaining_time":0.5359764188},
{"learn":[33.52268344],"iteration":917,"passed_time":5.92829102,"remaining_time":0.5295423351},
{"learn":[33.51309158],"iteration":918,"passed_time":5.934971631,"remaining_time":0.5231041373},
{"learn":[33.49565785],"iteration":919,"passed_time":5.940602642,"remaining_time":0.5165741427},
{"learn":[33.4827134],"iteration":920,"passed_time":5.947324758,"remaining_time":0.5101396915},
{"learn":[33.46390127],"iteration":921,"passed_time":5.953505863,"remaining_time":0.5036588474},
{"learn":[33.44442886],"iteration":922,"passed_time":5.960070103,"remaining_time":0.4972106153},
{"learn":[33.42433731],"iteration":923,"passed_time":5.966277587,"remaining_time":0.4907327885},
{"learn":[33.41158344],"iteration":924,"passed_time":5.972695214,"remaining_time":0.4842725849},
{"learn":[33.38586403],"iteration":925,"passed_time":5.978623839,"remaining_time":0.4777733953},
{"learn":[33.36937558],"iteration":926,"passed_time":5.984917137,"remaining_time":0.4713041543},
{"learn":[33.35577739],"iteration":927,"passed_time":5.990972158,"remaining_time":0.4648168053},
{"learn":[33.3516653],"iteration":928,"passed_time":5.996414974,"remaining_time":0.4582835987},
{"learn":[33.33864684],"iteration":929,"passed_time":6.002033545,"remaining_time":0.4517659658},
{"learn":[33.32368676],"iteration":930,"passed_time":6.008058064,"remaining_time":0.4452803506},
{"learn":[33.31117071],"iteration":931,"passed_time":6.013845385,"remaining_time":0.4387784186},
{"learn":[33.29703732],"iteration":932,"passed_time":6.019352573,"remaining_time":0.4322579018},
{"learn":[33.27901406],"iteration":933,"passed_time":6.02524756,"remaining_time":0.4257669582},
{"learn":[33.27257941],"iteration":934,"passed_time":6.030620882,"remaining_time":0.4192410239},
{"learn":[33.26191981],"iteration":935,"passed_time":6.036370297,"remaining_time":0.4127432682},
{"learn":[33.2479877],"iteration":936,"passed_time":6.042319232,"remaining_time":0.4062605246},
{"learn":[33.23564026],"iteration":937,"passed_time":6.050182122,"remaining_time":0.3999054281},
{"learn":[33.2232299],"iteration":938,"passed_time":6.072186815,"remaining_time":0.3944658101},
{"learn":[33.20535248],"iteration":939,"passed_time":6.122620668,"remaining_time":0.3908055745},
{"learn":[33.20078192],"iteration":940,"passed_time":6.128928869,"remaining_time":0.3842792808},
{"learn":[33.19213304],"iteration":941,"passed_time":6.137133643,"remaining_time":0.3778702243},
{"learn":[33.18249443],"iteration":942,"passed_time":6.144751236,"remaining_time":0.3714218668},
{"learn":[33.17034198],"iteration":943,"passed_time":6.150499237,"remaining_time":0.3648601243},
{"learn":[33.15641391],"iteration":944,"passed_time":6.157094263,"remaining_time":0.3583494016},
{"learn":[33.15437605],"iteration":945,"passed_time":6.162153224,"remaining_time":0.3517508183},
{"learn":[33.13012281],"iteration":946,"passed_time":6.167851847,"remaining_time":0.3451912861},
{"learn":[33.11562972],"iteration":947,"passed_time":6.175197048,"remaining_time":0.3387238887},
{"learn":[33.09473558],"iteration":948,"passed_time":6.183429845,"remaining_time":0.3323023415},
{"learn":[33.07154406],"iteration":949,"passed_time":6.18989275,"remaining_time":0.3257838289},
{"learn":[33.05515458],"iteration":950,"passed_time":6.19603838,"remaining_time":0.3192490858},
{"learn":[33.03955858],"iteration":951,"passed_time":6.202098044,"remaining_time":0.3127108257},
{"learn":[33.02532047],"iteration":952,"passed_time":6.208558445,"remaining_time":0.3061933336},
{"learn":[33.00524345],"iteration":953,"passed_time":6.216055317,"remaining_time":0.2997259377},
{"learn":[32.99061555],"iteration":954,"passed_time":6.222379437,"remaining_time":0.2932011253},
{"learn":[32.97278955],"iteration":955,"passed_time":6.228239169,"remaining_time":0.2866553592},
{"learn":[32.95952957],"iteration":956,"passed_time":6.233559132,"remaining_time":0.280086774},
{"learn":[32.9473843],"iteration":957,"passed_time":6.23939829,"remaining_time":0.2735435576},
{"learn":[32.93652397],"iteration":958,"passed_time":6.244909705,"remaining_time":0.2669877976},
{"learn":[32.92953494],"iteration":959,"passed_time":6.250600107,"remaining_time":0.2604416711},
{"learn":[32.91952544],"iteration":960,"passed_time":6.256153762,"remaining_time":0.253891776},
{"learn":[32.90891429],"iteration":961,"passed_time":6.261745579,"remaining_time":0.2473454595},
{"learn":[32.90558298],"iteration":962,"passed_time":6.266954651,"remaining_time":0.2407864196},
{"learn":[32.9049797],"iteration":963,"passed_time":6.272221423,"remaining_time":0.2342323353},
{"learn":[32.89418303],"iteration":964,"passed_time":6.277788597,"remaining_time":0.2276918144},
{"learn":[32.87559139],"iteration":965,"passed_time":6.283599037,"remaining_time":0.2211618709},
{"learn":[32.866026],"iteration":966,"passed_time":6.289388715,"remaining_time":0.2146327069},
{"learn":[32.8619286],"iteration":967,"passed_time":6.294933033,"remaining_time":0.2080969598},
{"learn":[32.84510082],"iteration":968,"passed_time":6.300520625,"remaining_time":0.2015646433},
{"learn":[32.83789251],"iteration":969,"passed_time":6.306319431,"remaining_time":0.1950408071},
{"learn":[32.83408064],"iteration":970,"passed_time":6.311944673,"remaining_time":0.1885132806},
{"learn":[32.82004985],"iteration":971,"passed_time":6.317848706,"remaining_time":0.1819956417},
{"learn":[32.80531495],"iteration":972,"passed_time":6.323500236,"remaining_time":0.1754722573},
{"learn":[32.78641112],"iteration":973,"passed_time":6.329258022,"remaining_time":0.1689534996},
{"learn":[32.76145192],"iteration":974,"passed_time":6.335034622,"remaining_time":0.1624367852},
{"learn":[32.74597343],"iteration":975,"passed_time":6.340823107,"remaining_time":0.1559218797},
{"learn":[32.73376451],"iteration":976,"passed_time":6.346528618,"remaining_time":0.1494065079},
{"learn":[32.72636861],"iteration":977,"passed_time":6.351879254,"remaining_time":0.1428848094},
{"learn":[32.71145237],"iteration":978,"passed_time":6.357778353,"remaining_time":0.136377268},
{"learn":[32.69563031],"iteration":979,"passed_time":6.363378392,"remaining_time":0.1298648652},
{"learn":[32.69289281],"iteration":980,"passed_time":6.369024246,"remaining_time":0.1233552097},
{"learn":[32.6815645],"iteration":981,"passed_time":6.375028843,"remaining_time":0.1168538892},
{"learn":[32.66594187],"iteration":982,"passed_time":6.380613954,"remaining_time":0.1103463247},
{"learn":[32.65709336],"iteration":983,"passed_time":6.386192159,"remaining_time":0.1038405229},
{"learn":[32.64153616],"iteration":984,"passed_time":6.392004992,"remaining_time":0.09734017755},
{"learn":[32.63079385],"iteration":985,"passed_time":6.397891659,"remaining_time":0.09084227507},
{"learn":[32.61595955],"iteration":986,"passed_time":6.403559524,"remaining_time":0.0843427293},
{"learn":[32.60417453],"iteration":987,"passed_time":6.409256328,"remaining_time":0.07784521856},
{"learn":[32.59092306],"iteration":988,"passed_time":6.414831311,"remaining_time":0.07134797212},
{"learn":[32.58776474],"iteration":989,"passed_time":6.4204274,"remaining_time":0.06485280203},
{"learn":[32.58154535],"iteration":990,"passed_time":6.425533969,"remaining_time":0.05835500073},
{"learn":[32.56348467],"iteration":991,"passed_time":6.431117087,"remaining_time":0.05186384747},
{"learn":[32.55086184],"iteration":992,"passed_time":6.436699817,"remaining_time":0.04537452036},
{"learn":[32.54228782],"iteration":993,"passed_time":6.442414684,"remaining_time":0.03888781499},
{"learn":[32.53375722],"iteration":994,"passed_time":6.449045514,"remaining_time":0.03240726389},
{"learn":[32.52556891],"iteration":995,"passed_time":6.454455755,"remaining_time":0.02592150905},
{"learn":[32.51140715],"iteration":996,"passed_time":6.460403476,"remaining_time":0.01943952902},
{"learn":[32.50885607],"iteration":997,"passed_time":6.466062033,"remaining_time":0.01295804015},
{"learn":[32.49909188],"iteration":998,"passed_time":6.471530885,"remaining_time":0.006478008894},
{"learn":[32.49693284],"iteration":999,"passed_time":6.476737857,"remaining_time":0}
]}